Workbook
Name Slicer_Gender: #N/A
Name Slicer_Region: #N/A
Name Slicer_Store_Type: #N/A

Sheet Customer_Dim
A1: Customer_ID | B1: Name | C1: Age | D1: Gender | E1: City | F1: State | G1: Country | H1: Loyalty_Level
A2: CUST1000 | B2: sheena bonilla | C2: 55 | D2: Male | E2: Donaldton | F2: North Carolina | G2: USA
A3: CUST1001 | B3: Eugene Nelson | C3: 26 | D3: Female | E3: Phillipsmouth | F3: North Dakota | G3: USA | H3: Platinum
A4: CUST1002 | B4: dr. Benjamin Price | C4: 29 | D4: Female | E4: Kylebury | F4: Alabama | G4: USA | H4: Platinum
A5: CUST1003 | B5: jeremy harris | C5: 59 | D5: Female | E5: Thomastown | F5: Ohio | G5: USA | H5: Bronze
A6: CUST1004 | B6: Caroline Collins | C6: 64 | D6: Female | E6: Nicholasshire | F6: California | G6: USA | H6: Silver
A7: CUST1005 | B7: Christine Vaughn | C7: 24 | D7: Male | E7: East Amandamouth | F7: Oregon | G7: USA | H7: Bronze
A8: CUST1006 | B8: Amber Jackson | C8: 29 | D8: Female | E8: Deborahborough | F8: South Dakota | G8: USA | H8: Platinum
A9: CUST1007 | B9: Daniel Boyd | C9: 29 | D9: Female | E9: West Pamelafurt | F9: West Virginia | G9: USA | H9: Bronze
A10: CUST1008 | B10: Melissa Howard | C10: 53 | D10: Female | E10: Maynardton | F10: New Hampshire | G10: USA | H10: Gold
A11: CUST1009 | B11: Ms. Maria Leach | C11: 64 | D11: Male | E11: Melissashire | F11: Pennsylvania | G11: USA | H11: Platinum
A12: CUST1010 | B12: Dominic Page | C12: 53 | D12: Male | E12: Port Michaelburgh | F12: Pennsylvania | G12: USA | H12: Bronze
A13: CUST1011 | B13: Brian Lopez | C13: 28 | D13: Female | E13: East Krista | F13: New York | G13: USA | H13: Gold
A14: CUST1012 | B14: Kenneth Lambert | C14: 55 | D14: Female | E14: North Kathryn | F14: Kansas | G14: USA | H14: Platinum
... A19: CUST1017 | B19: Adam Cruz | C19: 60 | D19: Female | E19: Brandonville | F19: Georgia | G19: USA | H19: Platinum
A20: CUST1018 | B20: Rhonda Moss | C20: 43 | D20: Male | E20: South William | F20: Kansas | G20: USA
A21: CUST1019 | B21: Michael Torres | C21: 46 | D21: Female | E21: Gonzalezfort | F21: New Jersey | G21: USA | H21: Platinum
A22: CUST1020 | B22: Bridget Allen | C22: 59 | D22: Male | E22: Lake Shaneburgh | F22: Delaware | G22: USA | H22: Silver
A23: CUST1021 | B23: Jeff Martinez | C23: 36 | D23: Female | E23: Smithburgh | F23: Oklahoma | G23: USA | H23: Gold
A24: CUST1022 | B24: paul fox | C24: 33 | D24: Female | E24: Michaelton | F24: Hawaii | G24: USA | H24: Silver
A25: CUST1023 | B25: Jonathan Steele | C25: 52 | D25: Female | E25: Molinabury | F25: Oregon | G25: USA | H25: Silver
A26: CUST1024 | B26: Heather Collins | C26: 40 | D26: Male | E26: Rogerschester | F26: Idaho | G26: USA | H26: Platinum
A27: CUST1025 | B27: Diana Taylor | C27: 59 | D27: Female | E27: Vasqueztown | F27: California | G27: USA | H27: Bronze
A28: CUST1026 | B28: Amber Carlson | C28: 18 | D28: Female | E28: East Michellemouth | F28: Missouri | G28: USA | H28: Gold
A29: CUST1027 | B29: Leslie Johnson | C29: 31 | D29: Male | E29: Mollyshire | F29: Utah | G29: USA
A30: CUST1028 | B30: Joshua Ryan | C30: 27 | D30: Female | E30: New David | F30: New Jersey | G30: USA | H30: Platinum
A31: CUST1029 | B31: David Arnold | C31: 54 | D31: Female | E31: East Jennifer | F31: California | G31: USA | H31: Silver
A32: CUST1030 | B32: Jessica Acevedo | C32: 64 | D32: Female | E32: Amybury | F32: Pennsylvania | G32: USA | H32: Bronze
A33: CUST1031 | B33: Sarah Vance | C33: 41 | D33: Male | E33: Johnsonville | F33: Oregon | G33: USA | H33: Silver
A34: CUST1032 | B34: Mike Jennings | C34: 48 | D34: Female | E34: Fostermouth | F34: Arizona | G34: USA | H34: Gold
A35: CUST1033 | B35: Robert Jones DDS | C35: 25 | D35: Male | E35: Tristanton | F35: Oklahoma | G35: USA | H35: Platinum
A36: CUST1034 | B36: Christopher Olson | C36: 27 | D36: Female | E36: West Richard | F36: Maryland | G36: USA | H36: Platinum
A37: CUST1035 | B37: Rachel Myers | C37: 52 | D37: Male | E37: Robertberg | F37: North Dakota | G37: USA | H37: Silver
A38: CUST1036 | B38: Thomas Phillips | C38: 20 | D38: Female | E38: Luisfurt | F38: Georgia | G38: USA | H38: Gold
A39: CUST1037 | B39: Christopher Carter | C39: 27 | D39: Female | E39: Brendastad | F39: South Dakota | G39: USA
A40: CUST1038 | B40: Deanna Simpson | C40: 35 | D40: Female | E40: Brownport | F40: North Dakota | G40: USA | H40: Bronze
A41: CUST1039 | B41: Tonya Reynolds | C41: 55 | D41: Female | E41: Darleneton | F41: Michigan | G41: USA | H41: Gold
A42: CUST1040 | B42: Eric Vega | C42: 50 | D42: Male | E42: Williamsonland | F42: Kansas | G42: USA | H42: Gold
A43: CUST1041 | B43: James Gibbs | C43: 21 | D43: Male | E43: Mooneyshire | F43: Alaska | G43: USA | H43: Platinum
A44: CUST1042 | B44: William Martin | C44: 19 | D44: Male | E44: Ryanburgh | F44: Connecticut | G44: USA | H44: Platinum
A45: CUST1043 | B45: Joseph Snow | C45: 45 | D45: Male | E45: South Michaelfort | F45: Vermont | G45: USA | H45: Gold
A46: CUST1044 | B46: Denise Williams | C46: 34 | D46: Male | E46: Christianstad | F46: Hawaii | G46: USA | H46: Bronze
A47: CUST1045 | B47: Jordan Jackson DDS | C47: 54 | D47: Male | E47: North Johnview | F47: Arizona | G47: USA | H47: Gold
A48: CUST1046 | B48: Michelle Garcia DDS | C48: 55 | D48: Female | E48: Perezbury | F48: Ohio | G48: USA | H48: Platinum
A49: CUST1047 | B49: Gina Knight | C49: 54 | D49: Female | E49: Lake Roberthaven | F49: Nevada | G49: USA | H49: Silver
A50: CUST1048 | B50: April Mullins | C50: 54 | D50: Male | E50: Dawsonbury | F50: North Carolina | G50: USA | H50: Platinum
A51: CUST1049 | B51: Timothy Weaver | C51: 45 | D51: Female | E51: New Amy | F51: Ohio | G51: USA | H51: Gold
... A501: C-1499 | B501: Philip Pennington | C501: 27 | D501: Female | E501: East Valerieview | F501: Oregon | G501: USA | H501: Platinum

Sheet Customer_Dim_Cleaning
A1: Customer_ID | B1: Name | C1: Name2 | D1: Age | E1: Gender | F1: City | G1: City2 | H1: State | I1: Country | J1: Loyalty_Level | K1: Loyalty_Level2
A2: CUST1000 | B2: sheena bonilla | C2: =PROPER(TRIM(B2)) -> Sheena Bonilla | D2: 55 | E2: Male | F2: Donaldton | G2: =PROPER(TRIM(F2)) -> Donaldton | H2: North Carolina | I2: USA | K2: =IF(J2="","Platinum",J2) -> Platinum
A3: CUST1001 | B3: Eugene Nelson | C3: =PROPER(TRIM(B3)) -> Eugene Nelson | D3: 26 | E3: Female | F3: Phillipsmouth | G3: =PROPER(TRIM(F3)) -> Phillipsmouth | H3: North Dakota | I3: USA | J3: Platinum | K3: =IF(J3="","Platinum",J3) -> Platinum
A4: CUST1002 | B4: dr. Benjamin Price | C4: =PROPER(TRIM(B4)) -> Dr. Benjamin Price | D4: 29 | E4: Female | F4: Kylebury | G4: =PROPER(TRIM(F4)) -> Kylebury | H4: Alabama | I4: USA | J4: Platinum | K4: =IF(J4="","Platinum",J4) -> Platinum
A5: CUST1003 | B5: jeremy harris | C5: =PROPER(TRIM(B5)) -> Jeremy Harris | D5: 59 | E5: Female | F5: Thomastown | G5: =PROPER(TRIM(F5)) -> Thomastown | H5: Ohio | I5: USA | J5: Bronze | K5: =IF(J5="","Platinum",J5) -> Bronze
A6: CUST1004 | B6: Caroline Collins | C6: =PROPER(TRIM(B6)) -> Caroline Collins | D6: 64 | E6: Female | F6: Nicholasshire | G6: =PROPER(TRIM(F6)) -> Nicholasshire | H6: California | I6: USA | J6: Silver | K6: =IF(J6="","Platinum",J6) -> Silver
A7: CUST1005 | B7: Christine Vaughn | C7: =PROPER(TRIM(B7)) -> Christine Vaughn | D7: 24 | E7: Male | F7: East Amandamouth | G7: =PROPER(TRIM(F7)) -> East Amandamouth | H7: Oregon | I7: USA | J7: Bronze | K7: =IF(J7="","Platinum",J7) -> Bronze
A8: CUST1006 | B8: Amber Jackson | C8: =PROPER(TRIM(B8)) -> Amber Jackson | D8: 29 | E8: Female | F8: Deborahborough | G8: =PROPER(TRIM(F8)) -> Deborahborough | H8: South Dakota | I8: USA | J8: Platinum | K8: =IF(J8="","Platinum",J8) -> Platinum
A9: CUST1007 | B9: Daniel Boyd | C9: =PROPER(TRIM(B9)) -> Daniel Boyd | D9: 29 | E9: Female | F9: West Pamelafurt | G9: =PROPER(TRIM(F9)) -> West Pamelafurt | H9: West Virginia | I9: USA | J9: Bronze | K9: =IF(J9="","Platinum",J9) -> Bronze
A10: CUST1008 | B10: Melissa Howard | C10: =PROPER(TRIM(B10)) -> Melissa Howard | D10: 53 | E10: Female | F10: Maynardton | G10: =PROPER(TRIM(F10)) -> Maynardton | H10: New Hampshire | I10: USA | J10: Gold | K10: =IF(J10="","Platinum",J10) -> Gold
A11: CUST1009 | B11: Ms. Maria Leach | C11: =PROPER(TRIM(B11)) -> Ms. Maria Leach | D11: 64 | E11: Male | F11: Melissashire | G11: =PROPER(TRIM(F11)) -> Melissashire | H11: Pennsylvania | I11: USA | J11: Platinum | K11: =IF(J11="","Platinum",J11) -> Platinum
A12: CUST1010 | B12: Dominic Page | C12: =PROPER(TRIM(B12)) -> Dominic Page | D12: 53 | E12: Male | F12: Port Michaelburgh | G12: =PROPER(TRIM(F12)) -> Port Michaelburgh | H12: Pennsylvania | I12: USA | J12: Bronze | K12: =IF(J12="","Platinum",J12) -> Bronze
A13: CUST1011 | B13: Brian Lopez | C13: =PROPER(TRIM(B13)) -> Brian Lopez | D13: 28 | E13: Female | F13: East Krista | G13: =PROPER(TRIM(F13)) -> East Krista | H13: New York | I13: USA | J13: Gold | K13: =IF(J13="","Platinum",J13) -> Gold
A14: CUST1012 | B14: Kenneth Lambert | C14: =PROPER(TRIM(B14)) -> Kenneth Lambert | D14: 55 | E14: Female | F14: North Kathryn | G14: =PROPER(TRIM(F14)) -> North Kathryn | H14: Kansas | I14: USA | J14: Platinum | K14: =IF(J14="","Platinum",J14) -> Platinum
... A19: CUST1017 | B19: Adam Cruz | C19: =PROPER(TRIM(B19)) -> Adam Cruz | D19: 60 | E19: Female | F19: Brandonville | G19: =PROPER(TRIM(F19)) -> Brandonville | H19: Georgia | I19: USA | J19: Platinum | K19: =IF(J19="","Platinum",J19) -> Platinum
A20: CUST1018 | B20: Rhonda Moss | C20: =PROPER(TRIM(B20)) -> Rhonda Moss | D20: 43 | E20: Male | F20: South William | G20: =PROPER(TRIM(F20)) -> South William | H20: Kansas | I20: USA | K20: =IF(J20="","Platinum",J20) -> Platinum
A21: CUST1019 | B21: Michael Torres | C21: =PROPER(TRIM(B21)) -> Michael Torres | D21: 46 | E21: Female | F21: Gonzalezfort | G21: =PROPER(TRIM(F21)) -> Gonzalezfort | H21: New Jersey | I21: USA | J21: Platinum | K21: =IF(J21="","Platinum",J21) -> Platinum
A22: CUST1020 | B22: Bridget Allen | C22: =PROPER(TRIM(B22)) -> Bridget Allen | D22: 59 | E22: Male | F22: Lake Shaneburgh | G22: =PROPER(TRIM(F22)) -> Lake Shaneburgh | H22: Delaware | I22: USA | J22: Silver | K22: =IF(J22="","Platinum",J22) -> Silver
A23: CUST1021 | B23: Jeff Martinez | C23: =PROPER(TRIM(B23)) -> Jeff Martinez | D23: 36 | E23: Female | F23: Smithburgh | G23: =PROPER(TRIM(F23)) -> Smithburgh | H23: Oklahoma | I23: USA | J23: Gold | K23: =IF(J23="","Platinum",J23) -> Gold
A24: CUST1022 | B24: paul fox | C24: =PROPER(TRIM(B24)) -> Paul Fox | D24: 33 | E24: Female | F24: Michaelton | G24: =PROPER(TRIM(F24)) -> Michaelton | H24: Hawaii | I24: USA | J24: Silver | K24: =IF(J24="","Platinum",J24) -> Silver
A25: CUST1023 | B25: Jonathan Steele | C25: =PROPER(TRIM(B25)) -> Jonathan Steele | D25: 52 | E25: Female | F25: Molinabury | G25: =PROPER(TRIM(F25)) -> Molinabury | H25: Oregon | I25: USA | J25: Silver | K25: =IF(J25="","Platinum",J25) -> Silver
A26: CUST1024 | B26: Heather Collins | C26: =PROPER(TRIM(B26)) -> Heather Collins | D26: 40 | E26: Male | F26: Rogerschester | G26: =PROPER(TRIM(F26)) -> Rogerschester | H26: Idaho | I26: USA | J26: Platinum | K26: =IF(J26="","Platinum",J26) -> Platinum
A27: CUST1025 | B27: Diana Taylor | C27: =PROPER(TRIM(B27)) -> Diana Taylor | D27: 59 | E27: Female | F27: Vasqueztown | G27: =PROPER(TRIM(F27)) -> Vasqueztown | H27: California | I27: USA | J27: Bronze | K27: =IF(J27="","Platinum",J27) -> Bronze
A28: CUST1026 | B28: Amber Carlson | C28: =PROPER(TRIM(B28)) -> Amber Carlson | D28: 18 | E28: Female | F28: East Michellemouth | G28: =PROPER(TRIM(F28)) -> East Michellemouth | H28: Missouri | I28: USA | J28: Gold | K28: =IF(J28="","Platinum",J28) -> Gold
A29: CUST1027 | B29: Leslie Johnson | C29: =PROPER(TRIM(B29)) -> Leslie Johnson | D29: 31 | E29: Male | F29: Mollyshire | G29: =PROPER(TRIM(F29)) -> Mollyshire | H29: Utah | I29: USA | K29: =IF(J29="","Platinum",J29) -> Platinum
A30: CUST1028 | B30: Joshua Ryan | C30: =PROPER(TRIM(B30)) -> Joshua Ryan | D30: 27 | E30: Female | F30: New David | G30: =PROPER(TRIM(F30)) -> New David | H30: New Jersey | I30: USA | J30: Platinum | K30: =IF(J30="","Platinum",J30) -> Platinum
A31: CUST1029 | B31: David Arnold | C31: =PROPER(TRIM(B31)) -> David Arnold | D31: 54 | E31: Female | F31: East Jennifer | G31: =PROPER(TRIM(F31)) -> East Jennifer | H31: California | I31: USA | J31: Silver | K31: =IF(J31="","Platinum",J31) -> Silver
A32: CUST1030 | B32: Jessica Acevedo | C32: =PROPER(TRIM(B32)) -> Jessica Acevedo | D32: 64 | E32: Female | F32: Amybury | G32: =PROPER(TRIM(F32)) -> Amybury | H32: Pennsylvania | I32: USA | J32: Bronze | K32: =IF(J32="","Platinum",J32) -> Bronze
A33: CUST1031 | B33: Sarah Vance | C33: =PROPER(TRIM(B33)) -> Sarah Vance | D33: 41 | E33: Male | F33: Johnsonville | G33: =PROPER(TRIM(F33)) -> Johnsonville | H33: Oregon | I33: USA | J33: Silver | K33: =IF(J33="","Platinum",J33) -> Silver
A34: CUST1032 | B34: Mike Jennings | C34: =PROPER(TRIM(B34)) -> Mike Jennings | D34: 48 | E34: Female | F34: Fostermouth | G34: =PROPER(TRIM(F34)) -> Fostermouth | H34: Arizona | I34: USA | J34: Gold | K34: =IF(J34="","Platinum",J34) -> Gold
A35: CUST1033 | B35: Robert Jones DDS | C35: =PROPER(TRIM(B35)) -> Robert Jones Dds | D35: 25 | E35: Male | F35: Tristanton | G35: =PROPER(TRIM(F35)) -> Tristanton | H35: Oklahoma | I35: USA | J35: Platinum | K35: =IF(J35="","Platinum",J35) -> Platinum
A36: CUST1034 | B36: Christopher Olson | C36: =PROPER(TRIM(B36)) -> Christopher Olson | D36: 27 | E36: Female | F36: West Richard | G36: =PROPER(TRIM(F36)) -> West Richard | H36: Maryland | I36: USA | J36: Platinum | K36: =IF(J36="","Platinum",J36) -> Platinum
A37: CUST1035 | B37: Rachel Myers | C37: =PROPER(TRIM(B37)) -> Rachel Myers | D37: 52 | E37: Male | F37: Robertberg | G37: =PROPER(TRIM(F37)) -> Robertberg | H37: North Dakota | I37: USA | J37: Silver | K37: =IF(J37="","Platinum",J37) -> Silver
A38: CUST1036 | B38: Thomas Phillips | C38: =PROPER(TRIM(B38)) -> Thomas Phillips | D38: 20 | E38: Female | F38: Luisfurt | G38: =PROPER(TRIM(F38)) -> Luisfurt | H38: Georgia | I38: USA | J38: Gold | K38: =IF(J38="","Platinum",J38) -> Gold
A39: CUST1037 | B39: Christopher Carter | C39: =PROPER(TRIM(B39)) -> Christopher Carter | D39: 27 | E39: Female | F39: Brendastad | G39: =PROPER(TRIM(F39)) -> Brendastad | H39: South Dakota | I39: USA | K39: =IF(J39="","Platinum",J39) -> Platinum
A40: CUST1038 | B40: Deanna Simpson | C40: =PROPER(TRIM(B40)) -> Deanna Simpson | D40: 35 | E40: Female | F40: Brownport | G40: =PROPER(TRIM(F40)) -> Brownport | H40: North Dakota | I40: USA | J40: Bronze | K40: =IF(J40="","Platinum",J40) -> Bronze
A41: CUST1039 | B41: Tonya Reynolds | C41: =PROPER(TRIM(B41)) -> Tonya Reynolds | D41: 55 | E41: Female | F41: Darleneton | G41: =PROPER(TRIM(F41)) -> Darleneton | H41: Michigan | I41: USA | J41: Gold | K41: =IF(J41="","Platinum",J41) -> Gold
A42: CUST1040 | B42: Eric Vega | C42: =PROPER(TRIM(B42)) -> Eric Vega | D42: 50 | E42: Male | F42: Williamsonland | G42: =PROPER(TRIM(F42)) -> Williamsonland | H42: Kansas | I42: USA | J42: Gold | K42: =IF(J42="","Platinum",J42) -> Gold
A43: CUST1041 | B43: James Gibbs | C43: =PROPER(TRIM(B43)) -> James Gibbs | D43: 21 | E43: Male | F43: Mooneyshire | G43: =PROPER(TRIM(F43)) -> Mooneyshire | H43: Alaska | I43: USA | J43: Platinum | K43: =IF(J43="","Platinum",J43) -> Platinum
A44: CUST1042 | B44: William Martin | C44: =PROPER(TRIM(B44)) -> William Martin | D44: 19 | E44: Male | F44: Ryanburgh | G44: =PROPER(TRIM(F44)) -> Ryanburgh | H44: Connecticut | I44: USA | J44: Platinum | K44: =IF(J44="","Platinum",J44) -> Platinum
A45: CUST1043 | B45: Joseph Snow | C45: =PROPER(TRIM(B45)) -> Joseph Snow | D45: 45 | E45: Male | F45: South Michaelfort | G45: =PROPER(TRIM(F45)) -> South Michaelfort | H45: Vermont | I45: USA | J45: Gold | K45: =IF(J45="","Platinum",J45) -> Gold
A46: CUST1044 | B46: Denise Williams | C46: =PROPER(TRIM(B46)) -> Denise Williams | D46: 34 | E46: Male | F46: Christianstad | G46: =PROPER(TRIM(F46)) -> Christianstad | H46: Hawaii | I46: USA | J46: Bronze | K46: =IF(J46="","Platinum",J46) -> Bronze
A47: CUST1045 | B47: Jordan Jackson DDS | C47: =PROPER(TRIM(B47)) -> Jordan Jackson Dds | D47: 54 | E47: Male | F47: North Johnview | G47: =PROPER(TRIM(F47)) -> North Johnview | H47: Arizona | I47: USA | J47: Gold | K47: =IF(J47="","Platinum",J47) -> Gold
A48: CUST1046 | B48: Michelle Garcia DDS | C48: =PROPER(TRIM(B48)) -> Michelle Garcia Dds | D48: 55 | E48: Female | F48: Perezbury | G48: =PROPER(TRIM(F48)) -> Perezbury | H48: Ohio | I48: USA | J48: Platinum | K48: =IF(J48="","Platinum",J48) -> Platinum
A49: CUST1047 | B49: Gina Knight | C49: =PROPER(TRIM(B49)) -> Gina Knight | D49: 54 | E49: Female | F49: Lake Roberthaven | G49: =PROPER(TRIM(F49)) -> Lake Roberthaven | H49: Nevada | I49: USA | J49: Silver | K49: =IF(J49="","Platinum",J49) -> Silver
A50: CUST1048 | B50: April Mullins | C50: =PROPER(TRIM(B50)) -> April Mullins | D50: 54 | E50: Male | F50: Dawsonbury | G50: =PROPER(TRIM(F50)) -> Dawsonbury | H50: North Carolina | I50: USA | J50: Platinum | K50: =IF(J50="","Platinum",J50) -> Platinum
A51: CUST1049 | B51: Timothy Weaver | C51: =PROPER(TRIM(B51)) -> Timothy Weaver | D51: 45 | E51: Female | F51: New Amy | G51: =PROPER(TRIM(F51)) -> New Amy | H51: Ohio | I51: USA | J51: Gold | K51: =IF(J51="","Platinum",J51) -> Gold
... A501: CUST1499 | B501: Philip Pennington | C501: =PROPER(TRIM(B501)) -> Philip Pennington | D501: 27 | E501: Female | F501: East Valerieview | G501: =PROPER(TRIM(F501)) -> East Valerieview | H501: Oregon | I501: USA | J501: Platinum | K501: =IF(J501="","Platinum",J501) -> Platinum

Sheet Customer_Dim_Cleaned
A1: Customer_ID | B1: Name | C1: Age | D1: Gender | E1: City | F1: State | G1: Country | H1: Loyalty_Level
A2: CUST1000 | B2: Sheena Bonilla | C2: 55 | D2: Male | E2: Donaldton | F2: North Carolina | G2: USA | H2: Platinum
A3: CUST1001 | B3: Eugene Nelson | C3: 26 | D3: Female | E3: Phillipsmouth | F3: North Dakota | G3: USA | H3: Platinum
A4: CUST1002 | B4: Dr. Benjamin Price | C4: 29 | D4: Female | E4: Kylebury | F4: Alabama | G4: USA | H4: Platinum
A5: CUST1003 | B5: Jeremy Harris | C5: 59 | D5: Female | E5: Thomastown | F5: Ohio | G5: USA | H5: Bronze
A6: CUST1004 | B6: Caroline Collins | C6: 64 | D6: Female | E6: Nicholasshire | F6: California | G6: USA | H6: Silver
A7: CUST1005 | B7: Christine Vaughn | C7: 24 | D7: Male | E7: East Amandamouth | F7: Oregon | G7: USA | H7: Bronze
A8: CUST1006 | B8: Amber Jackson | C8: 29 | D8: Female | E8: Deborahborough | F8: South Dakota | G8: USA | H8: Platinum
A9: CUST1007 | B9: Daniel Boyd | C9: 29 | D9: Female | E9: West Pamelafurt | F9: West Virginia | G9: USA | H9: Bronze
A10: CUST1008 | B10: Melissa Howard | C10: 53 | D10: Female | E10: Maynardton | F10: New Hampshire | G10: USA | H10: Gold
A11: CUST1009 | B11: Ms. Maria Leach | C11: 64 | D11: Male | E11: Melissashire | F11: Pennsylvania | G11: USA | H11: Platinum
A12: CUST1010 | B12: Dominic Page | C12: 53 | D12: Male | E12: Port Michaelburgh | F12: Pennsylvania | G12: USA | H12: Bronze
A13: CUST1011 | B13: Brian Lopez | C13: 28 | D13: Female | E13: East Krista | F13: New York | G13: USA | H13: Gold
... A501: CUST1499 | B501: Philip Pennington | C501: 27 | D501: Female | E501: East Valerieview | F501: Oregon | G501: USA | H501: Platinum

Sheet Product_Dim
A1: Product_ID | B1: Product_Name | C1: Category | D1: Sub_Category | E1: Brand | F1: Cost | G1: Stock
A2: PROD0 | B2: Brother Laser Printer | C2: Electronics | D2: Computer | E2: Hunt Inc | F2: 112.42 | G2: 416
A3: PROD1 | B3: Men's Graphic T-Shirt | C3: Clothing | D3: Tops | E3: Terry-Moore | F3: 342.56 | G3: 181
A4: PROD2 | B4: Women's Casual Hoodie | C4: Clothing | D4: Outerwear | E4: Sims Inc | G4: 352
A5: P-3 | B5: Men's Running Jacket | C5: Clothing | D5: Outerwear | E5: Pineda Ltd | F5: 364.67 | G5: 452
A6: PROD4 | B6: Women's Yoga Pants | C6: Clothing | D6: Bottoms | E6: Gonzales-Davis | F6: 306.46 | G6: 487
A7: PROD5 | B7: Men's Leather Belt | C7: Clothing | D7: Accessories | E7: Baldwin, Garza and Gonzalez | F7: 261 | G7: 59
A8: PROD6 | B8: Herbal Face Moisturizer | C8: Beauty | D8: Skincare | E8: Davidson PLC | F8: 312.8 | G8: 350
A9: PROD7 | B9: LED Table Lamp | C9: Home | D9: Lighting | E9: Harrell LLC | F9: 218.86 | G9: 170
A10: PROD8 | B10: Wireless Bluetooth Earbuds | C10: Electronics | D10: Audio | E10: Perez-Johnston | F10: 439.07 | G10: 142
A11: PROD9 | B11: Adjustable Dumbbell Set | C11: Sports | D11: Fitness | E11: Hill PLC | F11: 495.72 | G11: 323
A12: PROD10 | B12: Ceramic Kitchen Bowl Set | C12: Home | D12: Kitchen | E12: Hamilton Group | F12: 298.86 | G12: 308
A13: PROD11 | B13: HD Smart TV Stick | C13: Electronics | D13: Accessories | E13: Gibson, Hobbs and Weaver | F13: 449.4
A14: PROD12 | B14: Hair Strengthening Shampoo | C14: Beauty | D14: Haircare | E14: Rice LLC | F14: 115.82 | G14: 460
A15: PROD13 | B15: USB-C Fast Charger | C15: Electronics | D15: Accessories | E15: Dawson-Perkins | F15: 242.23 | G15: 453
A16: PROD14 | B16: Decorative Wall Mirror | C16: Home | D16: Decor | E16: Luna, Anderson and Bowman | F16: 48.01 | G16: 439
A17: PROD15 | B17: 4K Home Projector | C17: Electronics | D17: Appliances | E17: Thomas LLC | F17: 465.34 | G17: 301
A18: P-16 | B18: Beard Grooming Kit | C18: Beauty | D18: Grooming | E18: Erickson-Green | F18: 337.42 | G18: 256
A19: PROD17 | B19: Soccer Training Cone Set | C19: Sports | D19: Accessories | E19: Ford, Murphy and Wilson | F19: 144.53 | G19: 367
A20: PROD18 | B20: Women's Denim Jeans | C20: Clothing | D20: Bottoms | E20: Guerra-Hendrix | G20: 343
A21: PROD19 | B21: Knee Support Brace | C21: Sports | D21: Equipment | E21: May-Reese | F21: 21.34 | G21: 65
A22: PROD20 | B22: Outdoor Sports Water Bottle | C22: Sports | D22: Accessories | E22: Soto-Ellis | F22: 131.51
A23: PROD21 | B23: Multi-Purpose Storage Box | C23: Home | D23: Storage | E23: Gardner-Montes | F23: 123.46 | G23: 76
A24: PROD22 | B24: Carbon Fiber Tennis Racket | C24: Sports | D24: Equipment | E24: Flores, Pineda and Rodriguez | F24: 484.62 | G24: 432
A25: PROD23 | B25: Men's Formal Shirt | C25: Clothing | D25: Tops | E25: Moon, Mora and Santos | G25: 360
A26: PROD24 | B26: Foldable Camping Chair | C26: Sports | D26: Outdoor | E26: Cook Ltd | F26: 166.06 | G26: 340
A27: PROD25 | B27: Women's Scarf Set | C27: Clothing | D27: Accessories | E27: Brown and Sons | F27: 174.02 | G27: 268
A28: PROD26 | B28: Wireless Bluetooth Speaker | C28: Electronics | D28: Audio | E28: Reed-Schmidt | F28: 322.41 | G28: 213
A29: PROD27 | B29: Decorative Floor Vase | C29: Home | D29: Decor | E29: Khan, Jones and Paul | G29: 378
A30: PROD28 | B30: Sports Stopwatch Timer | C30: Sports | D30: Accessories | E30: Burns-Hansen | F30: 38.76 | G30: 137
A31: PROD29 | B31: Fabric Sofa Throw Blanket | C31: Home | D31: Decor | E31: Hoffman Group | F31: 218.48 | G31: 276
A32: PROD30 | B32: Stainless Steel Cutlery Set | C32: Home | D32: Kitchen | E32: Stevens, Fernandez and Martin | F32: 19.52 | G32: 57
A33: PROD31 | B33: Basketball | C33: Sports | D33: Team Sports | E33: Nolan-Snow | F33: 204.39 | G33: 281
A34: PROD32 | B34: Vitamin C Face Serum | C34: Beauty | D34: Skincare | E34: Griffin Ltd | F34: 283.83 | G34: 244
A35: PROD33 | B35: Modern Wall Clock | C35: Home | D35: Decor | E35: Weiss-Watson | F35: 179.77 | G35: 305
A36: PROD34 | B36: Gaming Mechanical Keyboard | C36: Electronics | D36: Computer | E36: Lucero LLC | F36: 419.28 | G36: 86
A37: PROD35 | B37: Bedroom Table Lamp | C37: Home | D37: Lighting | E37: Jones LLC | F37: 382.22 | G37: 329
A38: PROD36 | B38: Women's Summer Dress | C38: Clothing | D38: Tops | E38: Smith-Mills | F38: 223.43 | G38: 154
A39: PROD37 | B39: Men's Casual Sneakers | C39: Clothing | D39: Footwear | E39: Hogan-Lee | F39: 353.47 | G39: 214
A40: PROD38 | B40: Sports Water Hydration Pack | C40: Sports | D40: Outdoor | E40: Sims-Smith | F40: 135.61 | G40: 394
A41: PROD39 | B41: Portable Power Bank | C41: Electronics | D41: Mobile | E41: Cummings and Sons | F41: 326.06 | G41: 301
... A48: PROD46 | B48: Men's Winter Jacket | C48: Clothing | D48: Outerwear | E48: Kelly, Smith and Perez | F48: 167.34 | G48: 296
A49: PROD47 | B49: Makeup Brush Set | C49: Beauty | D49: Makeup | E49: Cook Inc | G49: 431
A50: PROD48 | B50: Car Dashboard Phone Holder | C50: Electronics | D50: Accessories | E50: Byrd, Stewart and Valdez | F50: 177.98 | G50: 103
A51: PROD49 | B51: Men's Roll-On Perfume | C51: Beauty | D51: Fragrance | E51: Sullivan and Sons | F51: 43.29 | G51: 267
A52: PROD50 | B52: Boxing Hand Wraps | C52: Sports | D52: Fitness | E52: Smith-King | F52: 190.29 | G52: 260
A53: PROD51 | B53: HDMI Cable – 2m | C53: Electronics | D53: Accessories | E53: Bautista, Green and Hale | F53: 88.49 | G53: 246
A54: PROD52 | B54: Rugby Ball | C54: Sports | D54: Team Sports | E54: Harris Inc | F54: 212.26 | G54: 82
A55: PROD53 | B55: Men's Track Pants | C55: Clothing | D55: Bottoms | E55: Hamilton, Woods and Walker | F55: 386.56 | G55: 125
A56: PROD54 | B56: Sports Stopwatch Pro | C56: Sports | D56: Accessories | E56: Thompson-French | F56: 434.84 | G56: 185
A57: PROD55 | B57: Ceramic Plant Pot | C57: Home | D57: Decor | E57: Hatfield, Baird and Torres | F57: 81.75
A58: PROD56 | B58: Premium Blanket Throw | C58: Home | D58: Decor | E58: Hernandez, Kennedy and Porter | F58: 461.47 | G58: 190
A59: PROD57 | B59: Foam Roller | C59: Sports | D59: Fitness | E59: Atkinson, Camacho and Oliver | F59: 30.62 | G59: 138
A60: PROD58 | B60: Womens Cotton Scarf | C60: Clothing | D60: Accessories | E60: Shepherd-Gould | F60: 113.83 | G60: 485
A61: PROD59 | B61: Men's Hair Styling Gel | C61: Beauty | D61: Haircare | E61: Cline-Mccarthy | F61: 17.31 | G61: 399
A62: PROD60 | B62: Luxury Perfume Spray | C62: Beauty | D62: Fragrance | E62: Gibson, Green and Lopez | F62: 482.75 | G62: 444
A63: PROD61 | B63: Tennis Ball 3-Pack | C63: Sports | D63: Equipment | E63: Lopez LLC | F63: 103.45 | G63: 465
A64: PROD62 | B64: Laptop Cooling Pad | C64: Electronics | D64: Computer | E64: Murray, Gould and Ware | F64: 86.42 | G64: 222
A65: PROD63 | B65: Organic Sunscreen Lotion | C65: Beauty | D65: Skincare | E65: Anderson-Riley | F65: 266.86 | G65: 458
A66: PROD64 | B66: Matte Lipstick Set | C66: Beauty | D66: Makeup | E66: Zhang Inc | F66: 299.11 | G66: 118
A67: PROD65 | B67: Adjustable Dumbbells 20kg | C67: Sports | D67: Fitness | E67: Montgomery, Benton and Miller | F67: 240.63 | G67: 423
A68: PROD66 | B68: Women's Hair Dryer Brush | C68: Beauty | D68: Haircare | E68: Torres, Spencer and Potter | F68: 340.39 | G68: 177
A69: PROD67 | B69: Smart LED Light Strip | C69: Electronics | D69: Accessories | E69: Flores-Davis | F69: 349.17 | G69: 476
... A84: PROD82 | B84: Fitness Resistance Bands | C84: Sports | D84: Fitness | E84: Reese-Watson | F84: 152.92 | G84: 281
A85: PROD83 | B85: Hydrating Face Cleanser | C85: Beauty | D85: Skincare | E85: Butler Group | G85: 159
A86: PROD84 | B86: Wooden Bookshelf | C86: Home | D86: Furniture | E86: Collins-Stephenson | F86: 388.46 | G86: 208
A87: PROD85 | B87: Women's Beanie Hat | C87: Clothing | D87: Accessories | E87: Richardson-Carrillo | F87: 119.57 | G87: 210
A88: PROD86 | B88: Kitchen Cutting Board | C88: Home | D88: Kitchen | E88: Taylor, Dodson and Johnston | F88: 176.07 | G88: 82
A89: PROD87 | B89: LED Bedside Lamp | C89: Home | D89: Lighting | E89: Aguilar, Horton and Lewis | F89: 371.38 | G89: 220
A90: PROD88 | B90: Sports Wrist Sweatbands | C90: Sports | D90: Accessories | E90: Olsen-Daniels | F90: 131.24 | G90: 232
A91: PROD89 | B91: Face Foundation Kit | C91: Beauty | D91: Makeup | E91: Taylor-Elliott | F91: 183.04 | G91: 457
A92: PROD90 | B92: Gaming Mouse Pad XL | C92: Electronics | D92: Accessories | E92: Sharp, Taylor and Rodriguez | F92: 340.14 | G92: 361
A93: PROD91 | B93: Women's High Heels | C93: Clothing | D93: Footwear | E93: Smith-Charles | F93: 438.25 | G93: 496
A94: PROD92 | B94: Microwave Oven | C94: Home | D94: Appliances | E94: Green, Powell and Palmer | F94: 447.43 | G94: 191
A95: PROD93 | B95: USB-C Laptop Charger | C95: Electronics | D95: Computer | E95: Martin LLC | F95: 377.52 | G95: 485
A96: PROD94 | B96: Vitamin E Body Lotion | C96: Beauty | D96: Skincare | E96: Hoffman-Williams | F96: 358.47 | G96: 213
A97: PROD95 | B97: Sports Stopwatch Basic | C97: Sports | D97: Accessories | E97: Wilson Group | F97: 60.65 | G97: 75
... A101: PROD99 | B101: Stainless Steel Cookware Set | C101: Home | D101: Kitchen | E101: Campbell Ltd | F101: 201.41 | G101: 146

Sheet Product_Dim_Cleaning
A1: Product_ID | B1: Product_Name | C1: Category | D1: Sub_Category | E1: Brand | F1: Cost | G1: Cost2 | H1: Stock | I1: Stock2
A2: PROD0 | B2: Brother Laser Printer | C2: Electronics | D2: Computer | E2: Hunt Inc | F2: 112.42 | G2: =IF(ISBLANK(F2),AVERAGEIF($C$2:$C$101,C2,$F$2:$F$101),F2) -> 112.42 | H2: 416 | I2: =IF(H2="",AVERAGEIF($D$2:$D$101,D2,$H$2:$H$101),H2) -> 416
A3: PROD1 | B3: Men's Graphic T-Shirt | C3: Clothing | D3: Tops | E3: Terry-Moore | F3: 342.56 | G3: =IF(ISBLANK(F3),AVERAGEIF($C$2:$C$101,C3,$F$2:$F$101),F3) -> 342.56 | H3: 181 | I3: =IF(H3="",AVERAGEIF($D$2:$D$101,D3,$H$2:$H$101),H3) -> 181
A4: PROD2 | B4: Women's Casual Hoodie | C4: Clothing | D4: Outerwear | E4: Sims Inc | G4: =IF(ISBLANK(F4),AVERAGEIF($C$2:$C$101,C4,$F$2:$F$101),F4) -> 265.73267 | H4: 352 | I4: =IF(H4="",AVERAGEIF($D$2:$D$101,D4,$H$2:$H$101),H4) -> 352
A5: PROD3 | B5: Men's Running Jacket | C5: Clothing | D5: Outerwear | E5: Pineda Ltd | F5: 364.67 | G5: =IF(ISBLANK(F5),AVERAGEIF($C$2:$C$101,C5,$F$2:$F$101),F5) -> 364.67 | H5: 452 | I5: =IF(H5="",AVERAGEIF($D$2:$D$101,D5,$H$2:$H$101),H5) -> 452
A6: PROD4 | B6: Women's Yoga Pants | C6: Clothing | D6: Bottoms | E6: Gonzales-Davis | F6: 306.46 | G6: =IF(ISBLANK(F6),AVERAGEIF($C$2:$C$101,C6,$F$2:$F$101),F6) -> 306.46 | H6: 487 | I6: =IF(H6="",AVERAGEIF($D$2:$D$101,D6,$H$2:$H$101),H6) -> 487
A7: PROD5 | B7: Men's Leather Belt | C7: Clothing | D7: Accessories | E7: Baldwin, Garza and Gonzalez | F7: 261 | G7: =IF(ISBLANK(F7),AVERAGEIF($C$2:$C$101,C7,$F$2:$F$101),F7) -> 261 | H7: 59 | I7: =IF(H7="",AVERAGEIF($D$2:$D$101,D7,$H$2:$H$101),H7) -> 59
A8: PROD6 | B8: Herbal Face Moisturizer | C8: Beauty | D8: Skincare | E8: Davidson PLC | F8: 312.8 | G8: =IF(ISBLANK(F8),AVERAGEIF($C$2:$C$101,C8,$F$2:$F$101),F8) -> 312.8 | H8: 350 | I8: =IF(H8="",AVERAGEIF($D$2:$D$101,D8,$H$2:$H$101),H8) -> 350
A9: PROD7 | B9: LED Table Lamp | C9: Home | D9: Lighting | E9: Harrell LLC | F9: 218.86 | G9: =IF(ISBLANK(F9),AVERAGEIF($C$2:$C$101,C9,$F$2:$F$101),F9) -> 218.86 | H9: 170 | I9: =IF(H9="",AVERAGEIF($D$2:$D$101,D9,$H$2:$H$101),H9) -> 170
A10: PROD8 | B10: Wireless Bluetooth Earbuds | C10: Electronics | D10: Audio | E10: Perez-Johnston | F10: 439.07 | G10: =IF(ISBLANK(F10),AVERAGEIF($C$2:$C$101,C10,$F$2:$F$101),F10) -> 439.07 | H10: 142 | I10: =IF(H10="",AVERAGEIF($D$2:$D$101,D10,$H$2:$H$101),H10) -> 142
A11: PROD9 | B11: Adjustable Dumbbell Set | C11: Sports | D11: Fitness | E11: Hill PLC | F11: 495.72 | G11: =IF(ISBLANK(F11),AVERAGEIF($C$2:$C$101,C11,$F$2:$F$101),F11) -> 495.72 | H11: 323 | I11: =IF(H11="",AVERAGEIF($D$2:$D$101,D11,$H$2:$H$101),H11) -> 323
A12: PROD10 | B12: Ceramic Kitchen Bowl Set | C12: Home | D12: Kitchen | E12: Hamilton Group | F12: 298.86 | G12: =IF(ISBLANK(F12),AVERAGEIF($C$2:$C$101,C12,$F$2:$F$101),F12) -> 298.86 | H12: 308 | I12: =IF(H12="",AVERAGEIF($D$2:$D$101,D12,$H$2:$H$101),H12) -> 308
A13: PROD11 | B13: HD Smart TV Stick | C13: Electronics | D13: Accessories | E13: Gibson, Hobbs and Weaver | F13: 449.4 | G13: =IF(ISBLANK(F13),AVERAGEIF($C$2:$C$101,C13,$F$2:$F$101),F13) -> 449.4 | I13: =IF(H13="",AVERAGEIF($D$2:$D$101,D13,$H$2:$H$101),H13) -> 269.73333
A14: PROD12 | B14: Hair Strengthening Shampoo | C14: Beauty | D14: Haircare | E14: Rice LLC | F14: 115.82 | G14: =IF(ISBLANK(F14),AVERAGEIF($C$2:$C$101,C14,$F$2:$F$101),F14) -> 115.82 | H14: 460 | I14: =IF(H14="",AVERAGEIF($D$2:$D$101,D14,$H$2:$H$101),H14) -> 460
A15: PROD13 | B15: USB-C Fast Charger | C15: Electronics | D15: Accessories | E15: Dawson-Perkins | F15: 242.23 | G15: =IF(ISBLANK(F15),AVERAGEIF($C$2:$C$101,C15,$F$2:$F$101),F15) -> 242.23 | H15: 453 | I15: =IF(H15="",AVERAGEIF($D$2:$D$101,D15,$H$2:$H$101),H15) -> 453
A16: PROD14 | B16: Decorative Wall Mirror | C16: Home | D16: Decor | E16: Luna, Anderson and Bowman | F16: 48.01 | G16: =IF(ISBLANK(F16),AVERAGEIF($C$2:$C$101,C16,$F$2:$F$101),F16) -> 48.01 | H16: 439 | I16: =IF(H16="",AVERAGEIF($D$2:$D$101,D16,$H$2:$H$101),H16) -> 439
A17: PROD15 | B17: 4K Home Projector | C17: Electronics | D17: Appliances | E17: Thomas LLC | F17: 465.34 | G17: =IF(ISBLANK(F17),AVERAGEIF($C$2:$C$101,C17,$F$2:$F$101),F17) -> 465.34 | H17: 301 | I17: =IF(H17="",AVERAGEIF($D$2:$D$101,D17,$H$2:$H$101),H17) -> 301
A18: PROD16 | B18: Beard Grooming Kit | C18: Beauty | D18: Grooming | E18: Erickson-Green | F18: 337.42 | G18: =IF(ISBLANK(F18),AVERAGEIF($C$2:$C$101,C18,$F$2:$F$101),F18) -> 337.42 | H18: 256 | I18: =IF(H18="",AVERAGEIF($D$2:$D$101,D18,$H$2:$H$101),H18) -> 256
A19: PROD17 | B19: Soccer Training Cone Set | C19: Sports | D19: Accessories | E19: Ford, Murphy and Wilson | F19: 144.53 | G19: =IF(ISBLANK(F19),AVERAGEIF($C$2:$C$101,C19,$F$2:$F$101),F19) -> 144.53 | H19: 367 | I19: =IF(H19="",AVERAGEIF($D$2:$D$101,D19,$H$2:$H$101),H19) -> 367
A20: PROD18 | B20: Women's Denim Jeans | C20: Clothing | D20: Bottoms | E20: Guerra-Hendrix | G20: =IF(ISBLANK(F20),AVERAGEIF($C$2:$C$101,C20,$F$2:$F$101),F20) -> 265.73267 | H20: 343 | I20: =IF(H20="",AVERAGEIF($D$2:$D$101,D20,$H$2:$H$101),H20) -> 343
A21: PROD19 | B21: Knee Support Brace | C21: Sports | D21: Equipment | E21: May-Reese | F21: 21.34 | G21: =IF(ISBLANK(F21),AVERAGEIF($C$2:$C$101,C21,$F$2:$F$101),F21) -> 21.34 | H21: 65 | I21: =IF(H21="",AVERAGEIF($D$2:$D$101,D21,$H$2:$H$101),H21) -> 65
A22: PROD20 | B22: Outdoor Sports Water Bottle | C22: Sports | D22: Accessories | E22: Soto-Ellis | F22: 131.51 | G22: =IF(ISBLANK(F22),AVERAGEIF($C$2:$C$101,C22,$F$2:$F$101),F22) -> 131.51 | I22: =IF(H22="",AVERAGEIF($D$2:$D$101,D22,$H$2:$H$101),H22) -> 269.73333
A23: PROD21 | B23: Multi-Purpose Storage Box | C23: Home | D23: Storage | E23: Gardner-Montes | F23: 123.46 | G23: =IF(ISBLANK(F23),AVERAGEIF($C$2:$C$101,C23,$F$2:$F$101),F23) -> 123.46 | H23: 76 | I23: =IF(H23="",AVERAGEIF($D$2:$D$101,D23,$H$2:$H$101),H23) -> 76
A24: PROD22 | B24: Carbon Fiber Tennis Racket | C24: Sports | D24: Equipment | E24: Flores, Pineda and Rodriguez | F24: 484.62 | G24: =IF(ISBLANK(F24),AVERAGEIF($C$2:$C$101,C24,$F$2:$F$101),F24) -> 484.62 | H24: 432 | I24: =IF(H24="",AVERAGEIF($D$2:$D$101,D24,$H$2:$H$101),H24) -> 432
A25: PROD23 | B25: Men's Formal Shirt | C25: Clothing | D25: Tops | E25: Moon, Mora and Santos | G25: =IF(ISBLANK(F25),AVERAGEIF($C$2:$C$101,C25,$F$2:$F$101),F25) -> 265.73267 | H25: 360 | I25: =IF(H25="",AVERAGEIF($D$2:$D$101,D25,$H$2:$H$101),H25) -> 360
A26: PROD24 | B26: Foldable Camping Chair | C26: Sports | D26: Outdoor | E26: Cook Ltd | F26: 166.06 | G26: =IF(ISBLANK(F26),AVERAGEIF($C$2:$C$101,C26,$F$2:$F$101),F26) -> 166.06 | H26: 340 | I26: =IF(H26="",AVERAGEIF($D$2:$D$101,D26,$H$2:$H$101),H26) -> 340
A27: PROD25 | B27: Women's Scarf Set | C27: Clothing | D27: Accessories | E27: Brown and Sons | F27: 174.02 | G27: =IF(ISBLANK(F27),AVERAGEIF($C$2:$C$101,C27,$F$2:$F$101),F27) -> 174.02 | H27: 268 | I27: =IF(H27="",AVERAGEIF($D$2:$D$101,D27,$H$2:$H$101),H27) -> 268
A28: PROD26 | B28: Wireless Bluetooth Speaker | C28: Electronics | D28: Audio | E28: Reed-Schmidt | F28: 322.41 | G28: =IF(ISBLANK(F28),AVERAGEIF($C$2:$C$101,C28,$F$2:$F$101),F28) -> 322.41 | H28: 213 | I28: =IF(H28="",AVERAGEIF($D$2:$D$101,D28,$H$2:$H$101),H28) -> 213
A29: PROD27 | B29: Decorative Floor Vase | C29: Home | D29: Decor | E29: Khan, Jones and Paul | G29: =IF(ISBLANK(F29),AVERAGEIF($C$2:$C$101,C29,$F$2:$F$101),F29) -> 234.806 | H29: 378 | I29: =IF(H29="",AVERAGEIF($D$2:$D$101,D29,$H$2:$H$101),H29) -> 378
A30: PROD28 | B30: Sports Stopwatch Timer | C30: Sports | D30: Accessories | E30: Burns-Hansen | F30: 38.76 | G30: =IF(ISBLANK(F30),AVERAGEIF($C$2:$C$101,C30,$F$2:$F$101),F30) -> 38.76 | H30: 137 | I30: =IF(H30="",AVERAGEIF($D$2:$D$101,D30,$H$2:$H$101),H30) -> 137
A31: PROD29 | B31: Fabric Sofa Throw Blanket | C31: Home | D31: Decor | E31: Hoffman Group | F31: 218.48 | G31: =IF(ISBLANK(F31),AVERAGEIF($C$2:$C$101,C31,$F$2:$F$101),F31) -> 218.48 | H31: 276 | I31: =IF(H31="",AVERAGEIF($D$2:$D$101,D31,$H$2:$H$101),H31) -> 276
A32: PROD30 | B32: Stainless Steel Cutlery Set | C32: Home | D32: Kitchen | E32: Stevens, Fernandez and Martin | F32: 19.52 | G32: =IF(ISBLANK(F32),AVERAGEIF($C$2:$C$101,C32,$F$2:$F$101),F32) -> 19.52 | H32: 57 | I32: =IF(H32="",AVERAGEIF($D$2:$D$101,D32,$H$2:$H$101),H32) -> 57
A33: PROD31 | B33: Basketball | C33: Sports | D33: Team Sports | E33: Nolan-Snow | F33: 204.39 | G33: =IF(ISBLANK(F33),AVERAGEIF($C$2:$C$101,C33,$F$2:$F$101),F33) -> 204.39 | H33: 281 | I33: =IF(H33="",AVERAGEIF($D$2:$D$101,D33,$H$2:$H$101),H33) -> 281
A34: PROD32 | B34: Vitamin C Face Serum | C34: Beauty | D34: Skincare | E34: Griffin Ltd | F34: 283.83 | G34: =IF(ISBLANK(F34),AVERAGEIF($C$2:$C$101,C34,$F$2:$F$101),F34) -> 283.83 | H34: 244 | I34: =IF(H34="",AVERAGEIF($D$2:$D$101,D34,$H$2:$H$101),H34) -> 244
A35: PROD33 | B35: Modern Wall Clock | C35: Home | D35: Decor | E35: Weiss-Watson | F35: 179.77 | G35: =IF(ISBLANK(F35),AVERAGEIF($C$2:$C$101,C35,$F$2:$F$101),F35) -> 179.77 | H35: 305 | I35: =IF(H35="",AVERAGEIF($D$2:$D$101,D35,$H$2:$H$101),H35) -> 305
A36: PROD34 | B36: Gaming Mechanical Keyboard | C36: Electronics | D36: Computer | E36: Lucero LLC | F36: 419.28 | G36: =IF(ISBLANK(F36),AVERAGEIF($C$2:$C$101,C36,$F$2:$F$101),F36) -> 419.28 | H36: 86 | I36: =IF(H36="",AVERAGEIF($D$2:$D$101,D36,$H$2:$H$101),H36) -> 86
A37: PROD35 | B37: Bedroom Table Lamp | C37: Home | D37: Lighting | E37: Jones LLC | F37: 382.22 | G37: =IF(ISBLANK(F37),AVERAGEIF($C$2:$C$101,C37,$F$2:$F$101),F37) -> 382.22 | H37: 329 | I37: =IF(H37="",AVERAGEIF($D$2:$D$101,D37,$H$2:$H$101),H37) -> 329
A38: PROD36 | B38: Women's Summer Dress | C38: Clothing | D38: Tops | E38: Smith-Mills | F38: 223.43 | G38: =IF(ISBLANK(F38),AVERAGEIF($C$2:$C$101,C38,$F$2:$F$101),F38) -> 223.43 | H38: 154 | I38: =IF(H38="",AVERAGEIF($D$2:$D$101,D38,$H$2:$H$101),H38) -> 154
A39: PROD37 | B39: Men's Casual Sneakers | C39: Clothing | D39: Footwear | E39: Hogan-Lee | F39: 353.47 | G39: =IF(ISBLANK(F39),AVERAGEIF($C$2:$C$101,C39,$F$2:$F$101),F39) -> 353.47 | H39: 214 | I39: =IF(H39="",AVERAGEIF($D$2:$D$101,D39,$H$2:$H$101),H39) -> 214
A40: PROD38 | B40: Sports Water Hydration Pack | C40: Sports | D40: Outdoor | E40: Sims-Smith | F40: 135.61 | G40: =IF(ISBLANK(F40),AVERAGEIF($C$2:$C$101,C40,$F$2:$F$101),F40) -> 135.61 | H40: 394 | I40: =IF(H40="",AVERAGEIF($D$2:$D$101,D40,$H$2:$H$101),H40) -> 394
A41: PROD39 | B41: Portable Power Bank | C41: Electronics | D41: Mobile | E41: Cummings and Sons | F41: 326.06 | G41: =IF(ISBLANK(F41),AVERAGEIF($C$2:$C$101,C41,$F$2:$F$101),F41) -> 326.06 | H41: 301 | I41: =IF(H41="",AVERAGEIF($D$2:$D$101,D41,$H$2:$H$101),H41) -> 301
... A48: PROD46 | B48: Men's Winter Jacket | C48: Clothing | D48: Outerwear | E48: Kelly, Smith and Perez | F48: 167.34 | G48: =IF(ISBLANK(F48),AVERAGEIF($C$2:$C$101,C48,$F$2:$F$101),F48) -> 167.34 | H48: 296 | I48: =IF(H48="",AVERAGEIF($D$2:$D$101,D48,$H$2:$H$101),H48) -> 296
A49: PROD47 | B49: Makeup Brush Set | C49: Beauty | D49: Makeup | E49: Cook Inc | G49: =IF(ISBLANK(F49),AVERAGEIF($C$2:$C$101,C49,$F$2:$F$101),F49) -> 250.41615 | H49: 431 | I49: =IF(H49="",AVERAGEIF($D$2:$D$101,D49,$H$2:$H$101),H49) -> 431
A50: PROD48 | B50: Car Dashboard Phone Holder | C50: Electronics | D50: Accessories | E50: Byrd, Stewart and Valdez | F50: 177.98 | G50: =IF(ISBLANK(F50),AVERAGEIF($C$2:$C$101,C50,$F$2:$F$101),F50) -> 177.98 | H50: 103 | I50: =IF(H50="",AVERAGEIF($D$2:$D$101,D50,$H$2:$H$101),H50) -> 103
A51: PROD49 | B51: Men's Roll-On Perfume | C51: Beauty | D51: Fragrance | E51: Sullivan and Sons | F51: 43.29 | G51: =IF(ISBLANK(F51),AVERAGEIF($C$2:$C$101,C51,$F$2:$F$101),F51) -> 43.29 | H51: 267 | I51: =IF(H51="",AVERAGEIF($D$2:$D$101,D51,$H$2:$H$101),H51) -> 267
A52: PROD50 | B52: Boxing Hand Wraps | C52: Sports | D52: Fitness | E52: Smith-King | F52: 190.29 | G52: =IF(ISBLANK(F52),AVERAGEIF($C$2:$C$101,C52,$F$2:$F$101),F52) -> 190.29 | H52: 260 | I52: =IF(H52="",AVERAGEIF($D$2:$D$101,D52,$H$2:$H$101),H52) -> 260
A53: PROD51 | B53: HDMI Cable – 2m | C53: Electronics | D53: Accessories | E53: Bautista, Green and Hale | F53: 88.49 | G53: =IF(ISBLANK(F53),AVERAGEIF($C$2:$C$101,C53,$F$2:$F$101),F53) -> 88.49 | H53: 246 | I53: =IF(H53="",AVERAGEIF($D$2:$D$101,D53,$H$2:$H$101),H53) -> 246
A54: PROD52 | B54: Rugby Ball | C54: Sports | D54: Team Sports | E54: Harris Inc | F54: 212.26 | G54: =IF(ISBLANK(F54),AVERAGEIF($C$2:$C$101,C54,$F$2:$F$101),F54) -> 212.26 | H54: 82 | I54: =IF(H54="",AVERAGEIF($D$2:$D$101,D54,$H$2:$H$101),H54) -> 82
A55: PROD53 | B55: Men's Track Pants | C55: Clothing | D55: Bottoms | E55: Hamilton, Woods and Walker | F55: 386.56 | G55: =IF(ISBLANK(F55),AVERAGEIF($C$2:$C$101,C55,$F$2:$F$101),F55) -> 386.56 | H55: 125 | I55: =IF(H55="",AVERAGEIF($D$2:$D$101,D55,$H$2:$H$101),H55) -> 125
A56: PROD54 | B56: Sports Stopwatch Pro | C56: Sports | D56: Accessories | E56: Thompson-French | F56: 434.84 | G56: =IF(ISBLANK(F56),AVERAGEIF($C$2:$C$101,C56,$F$2:$F$101),F56) -> 434.84 | H56: 185 | I56: =IF(H56="",AVERAGEIF($D$2:$D$101,D56,$H$2:$H$101),H56) -> 185
A57: PROD55 | B57: Ceramic Plant Pot | C57: Home | D57: Decor | E57: Hatfield, Baird and Torres | F57: 81.75 | G57: =IF(ISBLANK(F57),AVERAGEIF($C$2:$C$101,C57,$F$2:$F$101),F57) -> 81.75 | I57: =IF(H57="",AVERAGEIF($D$2:$D$101,D57,$H$2:$H$101),H57) -> 331.33333
A58: PROD56 | B58: Premium Blanket Throw | C58: Home | D58: Decor | E58: Hernandez, Kennedy and Porter | F58: 461.47 | G58: =IF(ISBLANK(F58),AVERAGEIF($C$2:$C$101,C58,$F$2:$F$101),F58) -> 461.47 | H58: 190 | I58: =IF(H58="",AVERAGEIF($D$2:$D$101,D58,$H$2:$H$101),H58) -> 190
A59: PROD57 | B59: Foam Roller | C59: Sports | D59: Fitness | E59: Atkinson, Camacho and Oliver | F59: 30.62 | G59: =IF(ISBLANK(F59),AVERAGEIF($C$2:$C$101,C59,$F$2:$F$101),F59) -> 30.62 | H59: 138 | I59: =IF(H59="",AVERAGEIF($D$2:$D$101,D59,$H$2:$H$101),H59) -> 138
A60: PROD58 | B60: Womens Cotton Scarf | C60: Clothing | D60: Accessories | E60: Shepherd-Gould | F60: 113.83 | G60: =IF(ISBLANK(F60),AVERAGEIF($C$2:$C$101,C60,$F$2:$F$101),F60) -> 113.83 | H60: 485 | I60: =IF(H60="",AVERAGEIF($D$2:$D$101,D60,$H$2:$H$101),H60) -> 485
A61: PROD59 | B61: Men's Hair Styling Gel | C61: Beauty | D61: Haircare | E61: Cline-Mccarthy | F61: 17.31 | G61: =IF(ISBLANK(F61),AVERAGEIF($C$2:$C$101,C61,$F$2:$F$101),F61) -> 17.31 | H61: 399 | I61: =IF(H61="",AVERAGEIF($D$2:$D$101,D61,$H$2:$H$101),H61) -> 399
A62: PROD60 | B62: Luxury Perfume Spray | C62: Beauty | D62: Fragrance | E62: Gibson, Green and Lopez | F62: 482.75 | G62: =IF(ISBLANK(F62),AVERAGEIF($C$2:$C$101,C62,$F$2:$F$101),F62) -> 482.75 | H62: 444 | I62: =IF(H62="",AVERAGEIF($D$2:$D$101,D62,$H$2:$H$101),H62) -> 444
A63: PROD61 | B63: Tennis Ball 3-Pack | C63: Sports | D63: Equipment | E63: Lopez LLC | F63: 103.45 | G63: =IF(ISBLANK(F63),AVERAGEIF($C$2:$C$101,C63,$F$2:$F$101),F63) -> 103.45 | H63: 465 | I63: =IF(H63="",AVERAGEIF($D$2:$D$101,D63,$H$2:$H$101),H63) -> 465
A64: PROD62 | B64: Laptop Cooling Pad | C64: Electronics | D64: Computer | E64: Murray, Gould and Ware | F64: 86.42 | G64: =IF(ISBLANK(F64),AVERAGEIF($C$2:$C$101,C64,$F$2:$F$101),F64) -> 86.42 | H64: 222 | I64: =IF(H64="",AVERAGEIF($D$2:$D$101,D64,$H$2:$H$101),H64) -> 222
A65: PROD63 | B65: Organic Sunscreen Lotion | C65: Beauty | D65: Skincare | E65: Anderson-Riley | F65: 266.86 | G65: =IF(ISBLANK(F65),AVERAGEIF($C$2:$C$101,C65,$F$2:$F$101),F65) -> 266.86 | H65: 458 | I65: =IF(H65="",AVERAGEIF($D$2:$D$101,D65,$H$2:$H$101),H65) -> 458
A66: PROD64 | B66: Matte Lipstick Set | C66: Beauty | D66: Makeup | E66: Zhang Inc | F66: 299.11 | G66: =IF(ISBLANK(F66),AVERAGEIF($C$2:$C$101,C66,$F$2:$F$101),F66) -> 299.11 | H66: 118 | I66: =IF(H66="",AVERAGEIF($D$2:$D$101,D66,$H$2:$H$101),H66) -> 118
A67: PROD65 | B67: Adjustable Dumbbells 20kg | C67: Sports | D67: Fitness | E67: Montgomery, Benton and Miller | F67: 240.63 | G67: =IF(ISBLANK(F67),AVERAGEIF($C$2:$C$101,C67,$F$2:$F$101),F67) -> 240.63 | H67: 423 | I67: =IF(H67="",AVERAGEIF($D$2:$D$101,D67,$H$2:$H$101),H67) -> 423
A68: PROD66 | B68: Women's Hair Dryer Brush | C68: Beauty | D68: Haircare | E68: Torres, Spencer and Potter | F68: 340.39 | G68: =IF(ISBLANK(F68),AVERAGEIF($C$2:$C$101,C68,$F$2:$F$101),F68) -> 340.39 | H68: 177 | I68: =IF(H68="",AVERAGEIF($D$2:$D$101,D68,$H$2:$H$101),H68) -> 177
A69: PROD67 | B69: Smart LED Light Strip | C69: Electronics | D69: Accessories | E69: Flores-Davis | F69: 349.17 | G69: =IF(ISBLANK(F69),AVERAGEIF($C$2:$C$101,C69,$F$2:$F$101),F69) -> 349.17 | H69: 476 | I69: =IF(H69="",AVERAGEIF($D$2:$D$101,D69,$H$2:$H$101),H69) -> 476
... A84: PROD82 | B84: Fitness Resistance Bands | C84: Sports | D84: Fitness | E84: Reese-Watson | F84: 152.92 | G84: =IF(ISBLANK(F84),AVERAGEIF($C$2:$C$101,C84,$F$2:$F$101),F84) -> 152.92 | H84: 281 | I84: =IF(H84="",AVERAGEIF($D$2:$D$101,D84,$H$2:$H$101),H84) -> 281
A85: PROD83 | B85: Hydrating Face Cleanser | C85: Beauty | D85: Skincare | E85: Butler Group | G85: =IF(ISBLANK(F85),AVERAGEIF($C$2:$C$101,C85,$F$2:$F$101),F85) -> 250.41615 | H85: 159 | I85: =IF(H85="",AVERAGEIF($D$2:$D$101,D85,$H$2:$H$101),H85) -> 159
A86: PROD84 | B86: Wooden Bookshelf | C86: Home | D86: Furniture | E86: Collins-Stephenson | F86: 388.46 | G86: =IF(ISBLANK(F86),AVERAGEIF($C$2:$C$101,C86,$F$2:$F$101),F86) -> 388.46 | H86: 208 | I86: =IF(H86="",AVERAGEIF($D$2:$D$101,D86,$H$2:$H$101),H86) -> 208
A87: PROD85 | B87: Women's Beanie Hat | C87: Clothing | D87: Accessories | E87: Richardson-Carrillo | F87: 119.57 | G87: =IF(ISBLANK(F87),AVERAGEIF($C$2:$C$101,C87,$F$2:$F$101),F87) -> 119.57 | H87: 210 | I87: =IF(H87="",AVERAGEIF($D$2:$D$101,D87,$H$2:$H$101),H87) -> 210
A88: PROD86 | B88: Kitchen Cutting Board | C88: Home | D88: Kitchen | E88: Taylor, Dodson and Johnston | F88: 176.07 | G88: =IF(ISBLANK(F88),AVERAGEIF($C$2:$C$101,C88,$F$2:$F$101),F88) -> 176.07 | H88: 82 | I88: =IF(H88="",AVERAGEIF($D$2:$D$101,D88,$H$2:$H$101),H88) -> 82
A89: PROD87 | B89: LED Bedside Lamp | C89: Home | D89: Lighting | E89: Aguilar, Horton and Lewis | F89: 371.38 | G89: =IF(ISBLANK(F89),AVERAGEIF($C$2:$C$101,C89,$F$2:$F$101),F89) -> 371.38 | H89: 220 | I89: =IF(H89="",AVERAGEIF($D$2:$D$101,D89,$H$2:$H$101),H89) -> 220
A90: PROD88 | B90: Sports Wrist Sweatbands | C90: Sports | D90: Accessories | E90: Olsen-Daniels | F90: 131.24 | G90: =IF(ISBLANK(F90),AVERAGEIF($C$2:$C$101,C90,$F$2:$F$101),F90) -> 131.24 | H90: 232 | I90: =IF(H90="",AVERAGEIF($D$2:$D$101,D90,$H$2:$H$101),H90) -> 232
A91: PROD89 | B91: Face Foundation Kit | C91: Beauty | D91: Makeup | E91: Taylor-Elliott | F91: 183.04 | G91: =IF(ISBLANK(F91),AVERAGEIF($C$2:$C$101,C91,$F$2:$F$101),F91) -> 183.04 | H91: 457 | I91: =IF(H91="",AVERAGEIF($D$2:$D$101,D91,$H$2:$H$101),H91) -> 457
A92: PROD90 | B92: Gaming Mouse Pad XL | C92: Electronics | D92: Accessories | E92: Sharp, Taylor and Rodriguez | F92: 340.14 | G92: =IF(ISBLANK(F92),AVERAGEIF($C$2:$C$101,C92,$F$2:$F$101),F92) -> 340.14 | H92: 361 | I92: =IF(H92="",AVERAGEIF($D$2:$D$101,D92,$H$2:$H$101),H92) -> 361
A93: PROD91 | B93: Women's High Heels | C93: Clothing | D93: Footwear | E93: Smith-Charles | F93: 438.25 | G93: =IF(ISBLANK(F93),AVERAGEIF($C$2:$C$101,C93,$F$2:$F$101),F93) -> 438.25 | H93: 496 | I93: =IF(H93="",AVERAGEIF($D$2:$D$101,D93,$H$2:$H$101),H93) -> 496
A94: PROD92 | B94: Microwave Oven | C94: Home | D94: Appliances | E94: Green, Powell and Palmer | F94: 447.43 | G94: =IF(ISBLANK(F94),AVERAGEIF($C$2:$C$101,C94,$F$2:$F$101),F94) -> 447.43 | H94: 191 | I94: =IF(H94="",AVERAGEIF($D$2:$D$101,D94,$H$2:$H$101),H94) -> 191
A95: PROD93 | B95: USB-C Laptop Charger | C95: Electronics | D95: Computer | E95: Martin LLC | F95: 377.52 | G95: =IF(ISBLANK(F95),AVERAGEIF($C$2:$C$101,C95,$F$2:$F$101),F95) -> 377.52 | H95: 485 | I95: =IF(H95="",AVERAGEIF($D$2:$D$101,D95,$H$2:$H$101),H95) -> 485
A96: PROD94 | B96: Vitamin E Body Lotion | C96: Beauty | D96: Skincare | E96: Hoffman-Williams | F96: 358.47 | G96: =IF(ISBLANK(F96),AVERAGEIF($C$2:$C$101,C96,$F$2:$F$101),F96) -> 358.47 | H96: 213 | I96: =IF(H96="",AVERAGEIF($D$2:$D$101,D96,$H$2:$H$101),H96) -> 213
A97: PROD95 | B97: Sports Stopwatch Basic | C97: Sports | D97: Accessories | E97: Wilson Group | F97: 60.65 | G97: =IF(ISBLANK(F97),AVERAGEIF($C$2:$C$101,C97,$F$2:$F$101),F97) -> 60.65 | H97: 75 | I97: =IF(H97="",AVERAGEIF($D$2:$D$101,D97,$H$2:$H$101),H97) -> 75
... A101: PROD99 | B101: Stainless Steel Cookware Set | C101: Home | D101: Kitchen | E101: Campbell Ltd | F101: 201.41 | G101: =IF(ISBLANK(F101),AVERAGEIF($C$2:$C$101,C101,$F$2:$F$101),F101) -> 201.41 | H101: 146 | I101: =IF(H101="",AVERAGEIF($D$2:$D$101,D101,$H$2:$H$101),H101) -> 146

Sheet Product_Dim_Cleaned
A1: Product_ID | B1: Product_Name | C1: Category | D1: Sub_Category | E1: Brand | F1: Cost | G1: Stock
A2: PROD0 | B2: Brother Laser Printer | C2: Electronics | D2: Computer | E2: Hunt Inc | F2: 112.42 | G2: 416
A3: PROD1 | B3: Men's Graphic T-Shirt | C3: Clothing | D3: Tops | E3: Terry-Moore | F3: 342.56 | G3: 181
A4: PROD2 | B4: Women's Casual Hoodie | C4: Clothing | D4: Outerwear | E4: Sims Inc | F4: 265.73267 | G4: 352
A5: PROD3 | B5: Men's Running Jacket | C5: Clothing | D5: Outerwear | E5: Pineda Ltd | F5: 364.67 | G5: 452
A6: PROD4 | B6: Women's Yoga Pants | C6: Clothing | D6: Bottoms | E6: Gonzales-Davis | F6: 306.46 | G6: 487
A7: PROD5 | B7: Men's Leather Belt | C7: Clothing | D7: Accessories | E7: Baldwin, Garza and Gonzalez | F7: 261 | G7: 59
A8: PROD6 | B8: Herbal Face Moisturizer | C8: Beauty | D8: Skincare | E8: Davidson PLC | F8: 312.8 | G8: 350
A9: PROD7 | B9: LED Table Lamp | C9: Home | D9: Lighting | E9: Harrell LLC | F9: 218.86 | G9: 170
A10: PROD8 | B10: Wireless Bluetooth Earbuds | C10: Electronics | D10: Audio | E10: Perez-Johnston | F10: 439.07 | G10: 142
A11: PROD9 | B11: Adjustable Dumbbell Set | C11: Sports | D11: Fitness | E11: Hill PLC | F11: 495.72 | G11: 323
A12: PROD10 | B12: Ceramic Kitchen Bowl Set | C12: Home | D12: Kitchen | E12: Hamilton Group | F12: 298.86 | G12: 308
A13: PROD11 | B13: HD Smart TV Stick | C13: Electronics | D13: Accessories | E13: Gibson, Hobbs and Weaver | F13: 449.4 | G13: 269.73333
... A101: PROD99 | B101: Stainless Steel Cookware Set | C101: Home | D101: Kitchen | E101: Campbell Ltd | F101: 201.41 | G101: 146

Sheet Store_Dim
A1: Store_ID | B1: Store_Name | C1: Region | D1: City | E1: Store_Type
A2: STORE0 | B2: Rivera-Warner | C2: East | D2: Washingtonfurt | E2: Flagship
A3: STORE1 | B3: Martinez, Adkins and Johnson | C3: North | D3: Danielmouth | E3: Flagship
A4: STORE2 | B4: Black-Horn | C4: South | D4: North Nancyview | E4: Outlet
A5: STORE3 | B5: Johnson-Wright | C5: North | D5: Hoodberg | E5: Outlet
A6: STORE4 | B6: Alexander Group | C6: South | D6: Port Sharon | E6: Online
A7: STORE5 | B7: Gray Ltd | C7: North | D7: New Michaelchester | E7: Outlet
A8: STORE6 | B8: Benson-Elliott | C8: East | D8: Port Josephberg | E8: Online
A9: STORE7 | B9: Martinez-Mullins | C9: South | D9: Williamsfurt | E9: Online
A10: STORE8 | B10: Bean, Jones and Park | C10: West | D10: Thompsonborough | E10: Online
A11: STORE9 | B11: Moore, Padilla and Butler | C11: South | D11: East Johnstad | E11: Flagship
A12: STORE10 | B12: Hill, Wagner and Ballard | C12: East | D12: East Davidville | E12: Online
... A21: STORE19 | B21: Mann-Austin | C21: East | D21: Vasquezborough | E21: Online

Sheet Store_Dim_Cleaned
A1: Store_ID | B1: Store_Name | C1: Region | D1: City | E1: Store_Type
A2: STORE0 | B2: Rivera-Warner | C2: East | D2: Washingtonfurt | E2: Flagship
A3: STORE1 | B3: Martinez, Adkins and Johnson | C3: North | D3: Danielmouth | E3: Flagship
A4: STORE2 | B4: Black-Horn | C4: South | D4: North Nancyview | E4: Outlet
A5: STORE3 | B5: Johnson-Wright | C5: North | D5: Hoodberg | E5: Outlet
A6: STORE4 | B6: Alexander Group | C6: South | D6: Port Sharon | E6: Online
A7: STORE5 | B7: Gray Ltd | C7: North | D7: New Michaelchester | E7: Outlet
A8: STORE6 | B8: Benson-Elliott | C8: East | D8: Port Josephberg | E8: Online
A9: STORE7 | B9: Martinez-Mullins | C9: South | D9: Williamsfurt | E9: Online
A10: STORE8 | B10: Bean, Jones and Park | C10: West | D10: Thompsonborough | E10: Online
A11: STORE9 | B11: Moore, Padilla and Butler | C11: South | D11: East Johnstad | E11: Flagship
A12: STORE10 | B12: Hill, Wagner and Ballard | C12: East | D12: East Davidville | E12: Online
... A21: STORE19 | B21: Mann-Austin | C21: East | D21: Vasquezborough | E21: Online

Sheet Sales_Fact
A1: Sales_ID | B1: Order_Date | C1: Customer_ID | D1: Product_ID | E1: Store_ID | F1: Quantity | G1: Unit_Price | H1: Discount | I1: Payment_Type | J1: Total_Amount
A2: SALE0 | B2: 45480 | C2: CUST1409 | D2: PROD97 | E2: STORE3 | F2: 1 | G2: 218.04 | H2: 0.09 | I2: Credit Card | J2: 198.4164
A3: SALE1 | B3: 45285 | C3: CUST1467 | D3: PROD74 | E3: STORE17 | F3: 3 | G3: 104.47 | H3: 0.27 | I3: PayPal | J3: 228.7893
A4: SALE2 | B4: 45446 | C4: CUST1056 | D4: PROD49 | E4: STORE8 | F4: 4 | G4: 914.05 | H4: 0.25 | I4: Credit Card | J4: 2742.15
A5: SALE3 | B5: 45259 | C5: CUST1346 | D5: PROD76 | E5: STORE8 | F5: 1 | G5: 921.51 | H5: 0.16 | I5: COD | J5: 774.0684
A6: SALE4 | B6: 45297 | C6: CUST1493 | D6: PROD59 | E6: STORE5 | F6: 3 | G6: 745.3 | H6: 0.18 | I6: Credit Card | J6: 1833.438
A7: SALE5 | B7: 45499 | C7: CUST1116 | D7: PROD15 | E7: STORE7 | F7: 3 | G7: 147.01 | H7: 0.19 | I7: COD | J7: 357.2343
A8: SALE6 | B8: 45850 | C8: CUST1016 | D8: PROD56 | E8: STORE4 | F8: 2 | G8: 785.31 | H8: 0.15 | I8: PayPal | J8: 1335.027
A9: SALE7 | B9: 45248 | C9: CUST1152 | D9: PROD70 | E9: STORE8 | F9: 4 | G9: 342.39 | H9: 0.23 | I9: PayPal | J9: 1054.5612
A10: SALE8 | B10: 45781 | C10: CUST1187 | D10: PROD99 | E10: STORE5 | G10: 448.25 | H10: 0.07 | I10: PayPal | J10: 1250.6175
A11: SALE9 | B11: 45869 | C11: CUST1464 | D11: PROD33 | E11: STORE0 | F11: 2 | G11: 873.17 | H11: 0.23 | I11: PayPal | J11: 1344.6818
A12: SALE10 | B12: 45335 | C12: CUST1065 | D12: PROD24 | E12: STORE14 | F12: 1 | G12: 278.63 | H12: 0.07 | I12: Credit Card | J12: 259.1259
A13: SALE11 | B13: 45801 | C13: CUST1320 | D13: PROD39 | E13: STORE1 | F13: 4 | G13: 286.92 | H13: 0.17 | I13: Credit Card | J13: 952.5744
A14: SALE12 | B14: 45528 | C14: CUST1237 | D14: PROD88 | E14: STORE4 | F14: 4 | G14: 644.58 | H14: 0.01 | I14: Credit Card | J14: 2552.5368
A15: SALE13 | B15: 45875 | C15: CUST1443 | D15: PROD34 | E15: STORE16 | F15: 2 | G15: 316.9 | H15: 0.3 | I15: PayPal | J15: 443.66
A16: SALE14 | B16: 45829 | C16: CUST1348 | D16: PROD24 | E16: STORE15 | F16: 4 | G16: 403.47 | H16: 0.29 | I16: PayPal | J16: 1145.8548
A17: SALE15 | B17: 45636 | C17: CUST1435 | D17: PROD36 | E17: STORE9 | G17: 871.34 | H17: 0.04 | I17: COD | J17: 2509.4592
A18: SALE16 | B18: 45913 | C18: CUST1276 | D18: PROD65 | E18: STORE19 | F18: 2 | G18: 451.98 | H18: 0.25 | I18: Credit Card | J18: 677.97
A19: SALE17 | B19: 45637 | C19: CUST1079 | D19: PROD27 | E19: STORE4 | F19: 2 | G19: 502.69 | H19: 0.23 | I19: Credit Card | J19: 774.1426
A20: SALE18 | B20: 45517 | C20: CUST1094 | D20: PROD39 | E20: STORE4 | F20: 2 | G20: 559.23 | H20: 0.25 | I20: COD | J20: 838.845
A21: SALE19 | B21: 45369 | C21: CUST1239 | D21: PROD60 | E21: STORE13 | F21: 4 | H21: 0.04 | I21: COD | J21: 1782.4512
A22: SALE20 | B22: 45843 | C22: CUST1144 | D22: PROD72 | E22: STORE17 | F22: 3 | G22: 986.04 | H22: 0.27 | I22: COD | J22: 2159.4276
A23: SALE21 | B23: 45447 | C23: CUST1396 | D23: PROD43 | E23: STORE18 | F23: 1 | G23: 589.56 | H23: 0.22 | I23: Credit Card | J23: 459.8568
A24: SALE22 | B24: 45394 | C24: CUST1476 | D24: PROD69 | E24: STORE10 | F24: 3 | G24: 979.42 | H24: 0.03 | I24: PayPal | J24: 2850.1122
A25: SALE23 | B25: 45466 | C25: CUST1368 | D25: PROD12 | E25: STORE8 | F25: 1 | G25: 719.28 | H25: 0.08 | I25: Credit Card | J25: 661.7376
A26: SALE24 | B26: 45908 | C26: CUST1186 | D26: PROD67 | E26: STORE6 | F26: 3 | G26: 77.6 | H26: 0.07 | I26: Credit Card | J26: 216.504
A27: SALE25 | B27: 45552 | C27: CUST1381 | D27: PROD5 | E27: STORE3 | F27: 4 | G27: 852.71 | H27: 0.14 | I27: PayPal | J27: 2933.3224
A28: SALE26 | B28: 45294 | C28: CUST1213 | D28: PROD98 | E28: STORE8 | F28: 4 | G28: 156.16 | I28: Credit Card | J28: 599.6544
A29: SALE27 | B29: 45710 | C29: CUST1200 | D29: PROD77 | E29: STORE8 | F29: 3 | G29: 815.49 | H29: 0.17 | I29: Credit Card | J29: 2030.5701
A30: SALE28 | B30: 45923 | C30: CUST1148 | D30: PROD13 | E30: STORE2 | F30: 2 | G30: 74.21 | H30: 0.11 | I30: PayPal | J30: 132.0938
A31: SALE29 | B31: 45302 | C31: CUST1348 | D31: PROD99 | E31: STORE3 | G31: 451.67 | H31: 0.15 | I31: Credit Card | J31: 1535.678
A32: SALE30 | B32: 45217 | C32: CUST1028 | D32: PROD5 | E32: STORE19 | F32: 1 | G32: 429.38 | H32: 0.13 | I32: PayPal | J32: 373.5606
A33: SALE31 | B33: 45593 | C33: CUST1412 | D33: PROD53 | E33: STORE12 | F33: 2 | G33: 148.96 | H33: 0.03 | I33: COD | J33: 288.9824
A34: SALE32 | B34: 45597 | C34: CUST1398 | D34: PROD75 | E34: STORE8 | F34: 4 | G34: 313.83 | H34: 0.08 | I34: Credit Card | J34: 1154.8944
A35: SALE33 | B35: 45620 | C35: CUST1453 | D35: PROD12 | E35: STORE6 | F35: 2 | G35: 717.31 | H35: 0.15 | I35: Credit Card | J35: 1219.427
A36: SALE34 | B36: 45215 | C36: CUST1344 | D36: PROD79 | E36: STORE1 | G36: 873.22 | H36: 0.18 | I36: Credit Card | J36: 2148.1212
A37: SALE35 | B37: 45878 | C37: CUST1218 | D37: PROD16 | E37: STORE3 | F37: 4 | G37: 109.36 | H37: 0.19 | I37: COD | J37: 354.3264
A38: SALE36 | B38: 45635 | C38: CUST1086 | D38: PROD5 | E38: STORE7 | F38: 3 | G38: 559.52 | H38: 0.16 | I38: PayPal | J38: 1409.9904
A39: SALE37 | B39: 45329 | C39: CUST1492 | D39: PROD10 | E39: STORE17 | F39: 3 | G39: 121.76 | H39: 0.27 | I39: PayPal | J39: 266.6544
A40: SALE38 | B40: 45378 | C40: CUST1189 | D40: PROD33 | E40: STORE13 | F40: 4 | G40: 735.32 | H40: 0.06 | I40: COD | J40: 2764.8032
A41: SALE39 | B41: 45264 | C41: CUST1431 | D41: PROD94 | E41: STORE3 | F41: 2 | G41: 600.73 | H41: 0.08 | I41: Credit Card | J41: 1105.3432
A42: SALE40 | B42: 45486 | C42: CUST1072 | D42: PROD26 | E42: STORE19 | F42: 2 | G42: 873.86 | H42: 0.07 | I42: COD | J42: 1625.3796
A43: SALE41 | B43: 45241 | C43: CUST1302 | D43: PROD23 | E43: STORE8 | F43: 3 | G43: 342.47 | H43: 0.08 | I43: PayPal | J43: 945.2172
A44: SALE42 | B44: 45649 | C44: CUST1335 | D44: PROD29 | E44: STORE9 | F44: 2 | G44: 915.15 | H44: 0.16 | I44: PayPal | J44: 1537.452
A45: SALE43 | B45: 45677 | C45: CUST1084 | D45: PROD33 | E45: STORE17 | G45: 863.11 | H45: 0.28 | I45: PayPal | J45: 1864.3176
A46: SALE44 | B46: 45538 | C46: CUST1203 | D46: PROD43 | E46: STORE12 | F46: 2 | G46: 209.32 | H46: 0.23 | I46: COD | J46: 322.3528
A47: SALE45 | B47: 45606 | C47: CUST1470 | D47: PROD59 | E47: STORE8 | F47: 4 | G47: 288.6 | H47: 0.09 | I47: PayPal | J47: 1050.504
A48: SALE46 | B48: 45570 | C48: CUST1070 | D48: PROD78 | E48: STORE16 | F48: 1 | G48: 418.69 | H48: 0.06 | I48: PayPal | J48: 393.5686
A49: SALE47 | B49: 45466 | C49: CUST1008 | D49: PROD30 | E49: STORE11 | F49: 1 | G49: 135.78 | H49: 0.14 | I49: PayPal | J49: 116.7708
A50: SALE48 | B50: 45218 | C50: CUST1203 | D50: PROD44 | E50: STORE17 | F50: 1 | G50: 517.13 | H50: 0.28 | I50: Credit Card | J50: 372.3336
A51: SALE49 | B51: 45607 | C51: CUST1420 | D51: PROD21 | E51: STORE16 | F51: 2 | G51: 384.66 | H51: 0.08 | I51: COD | J51: 707.7744
A52: SALE50 | B52: 45291 | C52: CUST1070 | D52: PROD52 | E52: STORE9 | F52: 3 | G52: 83.7 | H52: 0.24 | I52: PayPal | J52: 190.836
A53: SALE51 | B53: 45689 | C53: CUST1142 | D53: PROD69 | E53: STORE7 | F53: 3 | G53: 76.57 | H53: 0.26 | I53: Credit Card | J53: 169.9854
A54: SALE52 | B54: 45894 | C54: CUST1148 | D54: PROD89 | E54: STORE6 | F54: 3 | I54: Credit Card | J54: 486.0633
A55: SALE53 | B55: 45677 | C55: CUST1324 | D55: PROD20 | E55: STORE8 | F55: 1 | G55: 900.35 | H55: 0.13 | I55: COD | J55: 783.3045
A56: SALE54 | B56: 45706 | C56: CUST1095 | D56: PROD40 | E56: STORE10 | F56: 4 | G56: 428.09 | H56: 0.07 | I56: Credit Card | J56: 1592.4948
A57: SALE55 | B57: 45589 | C57: CUST1416 | D57: PROD49 | E57: STORE11 | F57: 2 | G57: 559.71 | H57: 0.3 | I57: COD | J57: 783.594
A58: SALE56 | B58: 45282 | C58: CUST1080 | D58: PROD34 | E58: STORE6 | F58: 2 | G58: 833.7 | H58: 0.06 | I58: PayPal | J58: 1567.356
A59: SALE57 | B59: 45462 | C59: CUST1467 | D59: PROD47 | E59: STORE14 | F59: 2 | G59: 680.16 | H59: 0.28 | I59: Credit Card | J59: 979.4304
A60: SALE58 | B60: 45633 | C60: CUST1404 | D60: PROD15 | E60: STORE7 | F60: 4 | G60: 733.42 | I60: PayPal | J60: 2552.3016
A61: SALE59 | B61: 45257 | C61: CUST1367 | D61: PROD89 | E61: STORE11 | F61: 1 | G61: 996.33 | H61: 0.23 | I61: PayPal | J61: 767.1741
A62: SALE60 | B62: 45854 | C62: CUST1408 | D62: PROD31 | E62: STORE10 | F62: 1 | G62: 198.83 | H62: 0.09 | I62: COD | J62: 180.9353
A63: SALE61 | B63: 45716 | C63: CUST1239 | D63: PROD19 | E63: STORE7 | F63: 1 | G63: 374.92 | H63: 0.18 | I63: PayPal | J63: 307.4344
A64: SALE62 | B64: 45515 | C64: CUST1464 | D64: PROD93 | E64: STORE16 | F64: 1 | G64: 468.94 | H64: 0.12 | I64: Credit Card | J64: 412.6672
A65: SALE63 | B65: 45927 | C65: CUST1126 | D65: PROD89 | E65: STORE12 | F65: 2 | G65: 121.37 | H65: 0.05 | I65: Credit Card | J65: 230.603
A66: SALE64 | B66: 45914 | C66: CUST1255 | D66: PROD53 | E66: STORE10 | F66: 3 | G66: 480.06 | H66: 0.01 | I66: Credit Card
A67: SALE65 | B67: 45290 | C67: CUST1162 | D67: PROD99 | E67: STORE17 | F67: 2 | G67: 856.57 | H67: 0.24 | I67: Credit Card | J67: 1301.9864
A68: SALE66 | B68: 45213 | C68: CUST1269 | D68: PROD77 | E68: STORE2 | F68: 4 | G68: 814.25 | H68: 0.18 | I68: Credit Card | J68: 2670.74
A69: SALE67 | B69: 45255 | C69: CUST1483 | D69: PROD12 | E69: STORE2 | F69: 1 | G69: 989.17 | H69: 0.2 | I69: PayPal | J69: 791.336
A70: SALE68 | B70: 45270 | C70: CUST1372 | D70: PROD72 | E70: STORE10 | F70: 4 | G70: 62.48 | H70: 0.18 | I70: Credit Card | J70: 204.9344
A71: SALE69 | B71: 45897 | C71: CUST1423 | D71: PROD13 | E71: STORE16 | F71: 4 | G71: 561.24 | H71: 0.24 | I71: Credit Card | J71: 1706.1696
A72: SALE70 | B72: 45849 | C72: CUST1058 | D72: PROD60 | E72: STORE5 | F72: 3 | G72: 92.24 | H72: 0.28 | I72: COD
A73: SALE71 | B73: 45889 | C73: CUST1168 | D73: PROD72 | E73: STORE1 | F73: 2 | G73: 668.3 | H73: 0.07 | I73: Credit Card | J73: 1243.038
A74: SALE72 | B74: 45533 | C74: CUST1409 | D74: PROD38 | E74: STORE5 | F74: 1 | G74: 553.82 | H74: 0.09 | I74: Credit Card | J74: 503.9762
A75: SALE73 | B75: 45626 | C75: CUST1037 | D75: PROD45 | E75: STORE11 | F75: 2 | G75: 556.43 | H75: 0.13 | I75: Credit Card | J75: 968.1882
A76: SALE74 | B76: 45942 | C76: CUST1273 | D76: PROD20 | E76: STORE8 | F76: 1 | G76: 184.98 | H76: 0.1 | I76: COD | J76: 166.482
A77: SALE75 | B77: 45500 | C77: CUST1035 | D77: PROD97 | E77: STORE12 | F77: 4 | G77: 700.18 | H77: 0.23 | I77: Credit Card | J77: 2156.5544
A78: SALE76 | B78: 45285 | C78: CUST1019 | D78: PROD76 | E78: STORE10 | F78: 2 | G78: 686.31 | H78: 0.25 | I78: Credit Card | J78: 1029.465
A79: SALE77 | B79: 45800 | C79: CUST1007 | D79: PROD67 | E79: STORE15 | F79: 1 | G79: 687.82 | H79: 0.27 | I79: COD | J79: 502.1086
A80: SALE78 | B80: 45609 | C80: CUST1221 | D80: PROD83 | E80: STORE8 | F80: 2 | G80: 900.55 | H80: 0.16 | I80: Credit Card | J80: 1512.924
A81: SALE79 | B81: 45268 | C81: CUST1115 | D81: PROD21 | E81: STORE2 | F81: 1 | G81: 341.17 | H81: 0.15 | I81: Credit Card | J81: 289.9945
A82: SALE80 | B82: 45885 | C82: CUST1176 | D82: PROD52 | E82: STORE8 | F82: 1 | G82: 442.27 | H82: 0.06 | I82: COD | J82: 415.7338
A83: SALE81 | B83: 45616 | C83: CUST1253 | D83: PROD71 | E83: STORE9 | F83: 1 | G83: 363.73 | H83: 0.25 | I83: PayPal | J83: 272.7975
A84: SALE82 | B84: 45518 | C84: CUST1378 | D84: PROD91 | E84: STORE17 | F84: 2 | G84: 601.33 | H84: 0.16 | I84: PayPal | J84: 1010.2344
A85: SALE83 | B85: 45427 | C85: CUST1403 | D85: PROD17 | E85: STORE18 | F85: 4 | G85: 34.39 | H85: 0.03 | I85: PayPal | J85: 133.4332
A86: SALE84 | B86: 45268 | C86: CUST1423 | D86: PROD46 | E86: STORE17 | F86: 1 | G86: 773.57 | H86: 0.05 | I86: COD
A87: SALE85 | B87: 45282 | C87: CUST1054 | D87: PROD88 | E87: STORE7 | F87: 4 | G87: 127.1 | H87: 0.24 | I87: COD | J87: 386.384
A88: SALE86 | B88: 45545 | C88: CUST1303 | D88: PROD20 | E88: STORE3 | F88: 3 | G88: 899.58 | H88: 0.28 | I88: PayPal | J88: 1943.0928
A89: SALE87 | B89: 45755 | C89: CUST1327 | D89: PROD1 | E89: STORE10 | F89: 3 | G89: 964.39 | H89: 0.04 | I89: Credit Card | J89: 2777.4432
A90: SALE88 | B90: 45588 | C90: CUST1183 | D90: PROD38 | E90: STORE0 | F90: 2 | G90: 217.83 | H90: 0.14 | I90: PayPal | J90: 374.6676
A91: SALE89 | B91: 45848 | C91: CUST1143 | D91: PROD17 | E91: STORE1 | F91: 4 | G91: 187.71 | H91: 0.06 | I91: COD | J91: 705.7896
A92: SALE90 | B92: 45577 | C92: CUST1010 | D92: PROD33 | E92: STORE18 | F92: 2 | G92: 350.12 | H92: 0.12 | I92: COD | J92: 616.2112
A93: SALE91 | B93: 45312 | C93: CUST1406 | D93: PROD16 | E93: STORE1 | F93: 4 | G93: 102.19 | H93: 0.17 | I93: PayPal | J93: 339.2708
A94: SALE92 | B94: 45350 | C94: CUST1007 | D94: PROD86 | E94: STORE4 | F94: 1 | G94: 696.53 | H94: 0.17 | I94: Credit Card | J94: 578.1199
A95: SALE93 | B95: 45657 | C95: CUST1065 | D95: PROD19 | E95: STORE4 | F95: 2 | G95: 327.52 | H95: 0.15 | I95: PayPal | J95: 556.784
A96: SALE94 | B96: 45530 | C96: CUST1298 | D96: PROD97 | E96: STORE19 | F96: 2 | G96: 569.36 | H96: 0.01 | I96: PayPal
A97: SALE95 | B97: 45556 | C97: CUST1321 | D97: PROD99 | E97: STORE6 | F97: 2 | G97: 68.29 | H97: 0.14 | I97: COD | J97: 117.4588
A98: SALE96 | B98: 45523 | C98: CUST1244 | D98: PROD50 | E98: STORE10 | F98: 1 | G98: 842.9 | H98: 0.06 | I98: COD | J98: 792.326
A99: SALE97 | B99: 45587 | C99: CUST1287 | D99: PROD3 | E99: STORE3 | F99: 3 | G99: 751.94 | H99: 0.26 | I99: PayPal | J99: 1669.3068
A100: SALE98 | B100: 45580 | C100: CUST1131 | D100: PROD56 | E100: STORE7 | F100: 4 | G100: 476.28 | H100: 0.17 | I100: Credit Card | J100: 1581.2496
...

Sheet Sales_Fact_Cleaning
A1: Sales_ID | B1: Order_Date | C1: Customer_ID | D1: Product_ID | E1: Store_ID | F1: Quantity | G1: Quantity | H1: Unit_Price | I1: Unit_Price | J1: Discount | K1: Discount | L1: Payment_Type | M1: Total_Amount | N1: Total Amount
A2: SALE0 | B2: 45480 | C2: CUST1409 | D2: PROD97 | E2: STORE3 | F2: 1 | G2: =IF(F2="",M2/(I2*(1-J2)),F2) -> 1 | H2: =VLOOKUP(D2,Product_Dim_Cleaned!A:F,6,FALSE) -> 245.98 | I2: =IF(H2="",VLOOKUP($D2,Product_Dim_Cleaned!$A$2:$F$101,6,FALSE),H2) -> 245.98 | J2: 0.09 | K2: =IF(J2="",1-(M2/(G2*I2)),J2) -> 0.09 | L2: Credit Card | M2: 198.4164 | N2: =IF(M2="",G2*I2*(1-K2),M2) -> 198.4164
A3: SALE1 | B3: 45285 | C3: CUST1467 | D3: PROD74 | E3: STORE17 | F3: 3 | G3: =IF(F3="",M3/(I3*(1-J3)),F3) -> 3 | H3: 104.47 | I3: =IF(H3="",VLOOKUP($D3,Product_Dim_Cleaned!$A$2:$F$101,6,FALSE),H3) -> 104.47 | J3: 0.27 | K3: =IF(J3="",1-(M3/(G3*I3)),J3) -> 0.27 | L3: PayPal | M3: 228.7893 | N3: =IF(M3="",G3*I3*(1-K3),M3) -> 228.7893
A4: SALE2 | B4: 45446 | C4: CUST1056 | D4: PROD49 | E4: STORE8 | F4: 4 | G4: =IF(F4="",M4/(I4*(1-J4)),F4) -> 4 | H4: 914.05 | I4: =IF(H4="",VLOOKUP($D4,Product_Dim_Cleaned!$A$2:$F$101,6,FALSE),H4) -> 914.05 | J4: 0.25 | K4: =IF(J4="",1-(M4/(G4*I4)),J4) -> 0.25 | L4: Credit Card | M4: 2742.15 | N4: =IF(M4="",G4*I4*(1-K4),M4) -> 2742.15
A5: SALE3 | B5: 45259 | C5: CUST1346 | D5: PROD76 | E5: STORE8 | F5: 1 | G5: =IF(F5="",M5/(I5*(1-J5)),F5) -> 1 | H5: 921.51 | I5: =IF(H5="",VLOOKUP($D5,Product_Dim_Cleaned!$A$2:$F$101,6,FALSE),H5) -> 921.51 | J5: 0.16 | K5: =IF(J5="",1-(M5/(G5*I5)),J5) -> 0.16 | L5: COD | M5: 774.0684 | N5: =IF(M5="",G5*I5*(1-K5),M5) -> 774.0684
A6: SALE4 | B6: 45297 | C6: CUST1493 | D6: PROD59 | E6: STORE5 | F6: 3 | G6: =IF(F6="",M6/(I6*(1-J6)),F6) -> 3 | H6: 745.3 | I6: =IF(H6="",VLOOKUP($D6,Product_Dim_Cleaned!$A$2:$F$101,6,FALSE),H6) -> 745.3 | J6: 0.18 | K6: =IF(J6="",1-(M6/(G6*I6)),J6) -> 0.18 | L6: Credit Card | M6: 1833.438 | N6: =IF(M6="",G6*I6*(1-K6),M6) -> 1833.438
A7: SALE5 | B7: 45499 | C7: CUST1116 | D7: PROD15 | E7: STORE7 | F7: 3 | G7: =IF(F7="",M7/(I7*(1-J7)),F7) -> 3 | H7: 147.01 | I7: =IF(H7="",VLOOKUP($D7,Product_Dim_Cleaned!$A$2:$F$101,6,FALSE),H7) -> 147.01 | J7: 0.19 | K7: =IF(J7="",1-(M7/(G7*I7)),J7) -> 0.19 | L7: COD | M7: 357.2343 | N7: =IF(M7="",G7*I7*(1-K7),M7) -> 357.2343
A8: SALE6 | B8: 45850 | C8: CUST1016 | D8: PROD56 | E8: STORE4 | F8: 2 | G8: =IF(F8="",M8/(I8*(1-J8)),F8) -> 2 | H8: 785.31 | I8: =IF(H8="",VLOOKUP($D8,Product_Dim_Cleaned!$A$2:$F$101,6,FALSE),H8) -> 785.31 | J8: 0.15 | K8: =IF(J8="",1-(M8/(G8*I8)),J8) -> 0.15 | L8: PayPal | M8: 1335.027 | N8: =IF(M8="",G8*I8*(1-K8),M8) -> 1335.027
A9: SALE7 | B9: 45248 | C9: CUST1152 | D9: PROD70 | E9: STORE8 | F9: 4 | G9: =IF(F9="",M9/(I9*(1-J9)),F9) -> 4 | H9: 342.39 | I9: =IF(H9="",VLOOKUP($D9,Product_Dim_Cleaned!$A$2:$F$101,6,FALSE),H9) -> 342.39 | J9: 0.23 | K9: =IF(J9="",1-(M9/(G9*I9)),J9) -> 0.23 | L9: PayPal | M9: 1054.5612 | N9: =IF(M9="",G9*I9*(1-K9),M9) -> 1054.5612
A10: SALE8 | B10: 45781 | C10: CUST1187 | D10: PROD99 | E10: STORE5 | G10: =IF(F10="",M10/(I10*(1-J10)),F10) -> 3 | H10: 448.25 | I10: =IF(H10="",VLOOKUP($D10,Product_Dim_Cleaned!$A$2:$F$101,6,FALSE),H10) -> 448.25 | J10: 0.07 | K10: =IF(J10="",1-(M10/(G10*I10)),J10) -> 0.07 | L10: PayPal | M10: 1250.6175 | N10: =IF(M10="",G10*I10*(1-K10),M10) -> 1250.6175
A11: SALE9 | B11: 45869 | C11: CUST1464 | D11: PROD33 | E11: STORE0 | F11: 2 | G11: =IF(F11="",M11/(I11*(1-J11)),F11) -> 2 | H11: 873.17 | I11: =IF(H11="",VLOOKUP($D11,Product_Dim_Cleaned!$A$2:$F$101,6,FALSE),H11) -> 873.17 | J11: 0.23 | K11: =IF(J11="",1-(M11/(G11*I11)),J11) -> 0.23 | L11: PayPal | M11: 1344.6818 | N11: =IF(M11="",G11*I11*(1-K11),M11) -> 1344.6818
A12: SALE10 | B12: 45335 | C12: CUST1065 | D12: PROD24 | E12: STORE14 | F12: 1 | G12: =IF(F12="",M12/(I12*(1-J12)),F12) -> 1 | H12: 278.63 | I12: =IF(H12="",VLOOKUP($D12,Product_Dim_Cleaned!$A$2:$F$101,6,FALSE),H12) -> 278.63 | J12: 0.07 | K12: =IF(J12="",1-(M12/(G12*I12)),J12) -> 0.07 | L12: Credit Card | M12: 259.1259 | N12: =IF(M12="",G12*I12*(1-K12),M12) -> 259.1259
A13: SALE11 | B13: 45801 | C13: CUST1320 | D13: PROD39 | E13: STORE1 | F13: 4 | G13: =IF(F13="",M13/(I13*(1-J13)),F13) -> 4 | H13: 286.92 | I13: =IF(H13="",VLOOKUP($D13,Product_Dim_Cleaned!$A$2:$F$101,6,FALSE),H13) -> 286.92 | J13: 0.17 | K13: =IF(J13="",1-(M13/(G13*I13)),J13) -> 0.17 | L13: Credit Card | M13: 952.5744 | N13: =IF(M13="",G13*I13*(1-K13),M13) -> 952.5744
A14: SALE12 | B14: 45528 | C14: CUST1237 | D14: PROD88 | E14: STORE4 | F14: 4 | G14: =IF(F14="",M14/(I14*(1-J14)),F14) -> 4 | H14: 644.58 | I14: =IF(H14="",VLOOKUP($D14,Product_Dim_Cleaned!$A$2:$F$101,6,FALSE),H14) -> 644.58 | J14: 0.01 | K14: =IF(J14="",1-(M14/(G14*I14)),J14) -> 0.01 | L14: Credit Card | M14: 2552.5368 | N14: =IF(M14="",G14*I14*(1-K14),M14) -> 2552.5368
A15: SALE13 | B15: 45875 | C15: CUST1443 | D15: PROD34 | E15: STORE16 | F15: 2 | G15: =IF(F15="",M15/(I15*(1-J15)),F15) -> 2 | H15: 316.9 | I15: =IF(H15="",VLOOKUP($D15,Product_Dim_Cleaned!$A$2:$F$101,6,FALSE),H15) -> 316.9 | J15: 0.3 | K15: =IF(J15="",1-(M15/(G15*I15)),J15) -> 0.3 | L15: PayPal | M15: 443.66 | N15: =IF(M15="",G15*I15*(1-K15),M15) -> 443.66
A16: SALE14 | B16: 45829 | C16: CUST1348 | D16: PROD24 | E16: STORE15 | F16: 4 | G16: =IF(F16="",M16/(I16*(1-J16)),F16) -> 4 | H16: 403.47 | I16: =IF(H16="",VLOOKUP($D16,Product_Dim_Cleaned!$A$2:$F$101,6,FALSE),H16) -> 403.47 | J16: 0.29 | K16: =IF(J16="",1-(M16/(G16*I16)),J16) -> 0.29 | L16: PayPal | M16: 1145.8548 | N16: =IF(M16="",G16*I16*(1-K16),M16) -> 1145.8548
A17: SALE15 | B17: 45636 | C17: CUST1435 | D17: PROD36 | E17: STORE9 | G17: =IF(F17="",M17/(I17*(1-J17)),F17) -> 3 | H17: 871.34 | I17: =IF(H17="",VLOOKUP($D17,Product_Dim_Cleaned!$A$2:$F$101,6,FALSE),H17) -> 871.34 | J17: 0.04 | K17: =IF(J17="",1-(M17/(G17*I17)),J17) -> 0.04 | L17: COD | M17: 2509.4592 | N17: =IF(M17="",G17*I17*(1-K17),M17) -> 2509.4592
A18: SALE16 | B18: 45913 | C18: CUST1276 | D18: PROD65 | E18: STORE19 | F18: 2 | G18: =IF(F18="",M18/(I18*(1-J18)),F18) -> 2 | H18: 451.98 | I18: =IF(H18="",VLOOKUP($D18,Product_Dim_Cleaned!$A$2:$F$101,6,FALSE),H18) -> 451.98 | J18: 0.25 | K18: =IF(J18="",1-(M18/(G18*I18)),J18) -> 0.25 | L18: Credit Card | M18: 677.97 | N18: =IF(M18="",G18*I18*(1-K18),M18) -> 677.97
A19: SALE17 | B19: 45637 | C19: CUST1079 | D19: PROD27 | E19: STORE4 | F19: 2 | G19: =IF(F19="",M19/(I19*(1-J19)),F19) -> 2 | H19: 502.69 | I19: =IF(H19="",VLOOKUP($D19,Product_Dim_Cleaned!$A$2:$F$101,6,FALSE),H19) -> 502.69 | J19: 0.23 | K19: =IF(J19="",1-(M19/(G19*I19)),J19) -> 0.23 | L19: Credit Card | M19: 774.1426 | N19: =IF(M19="",G19*I19*(1-K19),M19) -> 774.1426
A20: SALE18 | B20: 45517 | C20: CUST1094 | D20: PROD39 | E20: STORE4 | F20: 2 | G20: =IF(F20="",M20/(I20*(1-J20)),F20) -> 2 | H20: 559.23 | I20: =IF(H20="",VLOOKUP($D20,Product_Dim_Cleaned!$A$2:$F$101,6,FALSE),H20) -> 559.23 | J20: 0.25 | K20: =IF(J20="",1-(M20/(G20*I20)),J20) -> 0.25 | L20: COD | M20: 838.845 | N20: =IF(M20="",G20*I20*(1-K20),M20) -> 838.845
A21: SALE19 | B21: 45369 | C21: CUST1239 | D21: PROD60 | E21: STORE13 | F21: 4 | G21: =IF(F21="",M21/(I21*(1-J21)),F21) -> 4 | I21: =IF(H21="",VLOOKUP($D21,Product_Dim_Cleaned!$A$2:$F$101,6,FALSE),H21) -> 482.75 | J21: 0.04 | K21: =IF(J21="",1-(M21/(G21*I21)),J21) -> 0.04 | L21: COD | M21: 1782.4512 | N21: =IF(M21="",G21*I21*(1-K21),M21) -> 1782.4512
A22: SALE20 | B22: 45843 | C22: CUST1144 | D22: PROD72 | E22: STORE17 | F22: 3 | G22: =IF(F22="",M22/(I22*(1-J22)),F22) -> 3 | H22: 986.04 | I22: =IF(H22="",VLOOKUP($D22,Product_Dim_Cleaned!$A$2:$F$101,6,FALSE),H22) -> 986.04 | J22: 0.27 | K22: =IF(J22="",1-(M22/(G22*I22)),J22) -> 0.27 | L22: COD | M22: 2159.4276 | N22: =IF(M22="",G22*I22*(1-K22),M22) -> 2159.4276
A23: SALE21 | B23: 45447 | C23: CUST1396 | D23: PROD43 | E23: STORE18 | F23: 1 | G23: =IF(F23="",M23/(I23*(1-J23)),F23) -> 1 | H23: 589.56 | I23: =IF(H23="",VLOOKUP($D23,Product_Dim_Cleaned!$A$2:$F$101,6,FALSE),H23) -> 589.56 | J23: 0.22 | K23: =IF(J23="",1-(M23/(G23*I23)),J23) -> 0.22 | L23: Credit Card | M23: 459.8568 | N23: =IF(M23="",G23*I23*(1-K23),M23) -> 459.8568
A24: SALE22 | B24: 45394 | C24: CUST1476 | D24: PROD69 | E24: STORE10 | F24: 3 | G24: =IF(F24="",M24/(I24*(1-J24)),F24) -> 3 | H24: 979.42 | I24: =IF(H24="",VLOOKUP($D24,Product_Dim_Cleaned!$A$2:$F$101,6,FALSE),H24) -> 979.42 | J24: 0.03 | K24: =IF(J24="",1-(M24/(G24*I24)),J24) -> 0.03 | L24: PayPal | M24: 2850.1122 | N24: =IF(M24="",G24*I24*(1-K24),M24) -> 2850.1122
A25: SALE23 | B25: 45466 | C25: CUST1368 | D25: PROD12 | E25: STORE8 | F25: 1 | G25: =IF(F25="",M25/(I25*(1-J25)),F25) -> 1 | H25: 719.28 | I25: =IF(H25="",VLOOKUP($D25,Product_Dim_Cleaned!$A$2:$F$101,6,FALSE),H25) -> 719.28 | J25: 0.08 | K25: =IF(J25="",1-(M25/(G25*I25)),J25) -> 0.08 | L25: Credit Card | M25: 661.7376 | N25: =IF(M25="",G25*I25*(1-K25),M25) -> 661.7376
A26: SALE24 | B26: 45908 | C26: CUST1186 | D26: PROD67 | E26: STORE6 | F26: 3 | G26: =IF(F26="",M26/(I26*(1-J26)),F26) -> 3 | H26: 77.6 | I26: =IF(H26="",VLOOKUP($D26,Product_Dim_Cleaned!$A$2:$F$101,6,FALSE),H26) -> 77.6 | J26: 0.07 | K26: =IF(J26="",1-(M26/(G26*I26)),J26) -> 0.07 | L26: Credit Card | M26: 216.504 | N26: =IF(M26="",G26*I26*(1-K26),M26) -> 216.504
A27: SALE25 | B27: 45552 | C27: CUST1381 | D27: PROD5 | E27: STORE3 | F27: 4 | G27: =IF(F27="",M27/(I27*(1-J27)),F27) -> 4 | H27: 852.71 | I27: =IF(H27="",VLOOKUP($D27,Product_Dim_Cleaned!$A$2:$F$101,6,FALSE),H27) -> 852.71 | J27: 0.14 | K27: =IF(J27="",1-(M27/(G27*I27)),J27) -> 0.14 | L27: PayPal | M27: 2933.3224 | N27: =IF(M27="",G27*I27*(1-K27),M27) -> 2933.3224
A28: SALE26 | B28: 45294 | C28: CUST1213 | D28: PROD98 | E28: STORE8 | F28: 4 | G28: =IF(F28="",M28/(I28*(1-J28)),F28) -> 4 | H28: 156.16 | I28: =IF(H28="",VLOOKUP($D28,Product_Dim_Cleaned!$A$2:$F$101,6,FALSE),H28) -> 156.16 | K28: =IF(J28="",1-(M28/(G28*I28)),J28) -> 0.04 | L28: Credit Card | M28: 599.6544 | N28: =IF(M28="",G28*I28*(1-K28),M28) -> 599.6544
A29: SALE27 | B29: 45710 | C29: CUST1200 | D29: PROD77 | E29: STORE8 | F29: 3 | G29: =IF(F29="",M29/(I29*(1-J29)),F29) -> 3 | H29: 815.49 | I29: =IF(H29="",VLOOKUP($D29,Product_Dim_Cleaned!$A$2:$F$101,6,FALSE),H29) -> 815.49 | J29: 0.17 | K29: =IF(J29="",1-(M29/(G29*I29)),J29) -> 0.17 | L29: Credit Card | M29: 2030.5701 | N29: =IF(M29="",G29*I29*(1-K29),M29) -> 2030.5701
A30: SALE28 | B30: 45923 | C30: CUST1148 | D30: PROD13 | E30: STORE2 | F30: 2 | G30: =IF(F30="",M30/(I30*(1-J30)),F30) -> 2 | H30: 74.21 | I30: =IF(H30="",VLOOKUP($D30,Product_Dim_Cleaned!$A$2:$F$101,6,FALSE),H30) -> 74.21 | J30: 0.11 | K30: =IF(J30="",1-(M30/(G30*I30)),J30) -> 0.11 | L30: PayPal | M30: 132.0938 | N30: =IF(M30="",G30*I30*(1-K30),M30) -> 132.0938
A31: SALE29 | B31: 45302 | C31: CUST1348 | D31: PROD99 | E31: STORE3 | G31: =IF(F31="",M31/(I31*(1-J31)),F31) -> 4 | H31: 451.67 | I31: =IF(H31="",VLOOKUP($D31,Product_Dim_Cleaned!$A$2:$F$101,6,FALSE),H31) -> 451.67 | J31: 0.15 | K31: =IF(J31="",1-(M31/(G31*I31)),J31) -> 0.15 | L31: Credit Card | M31: 1535.678 | N31: =IF(M31="",G31*I31*(1-K31),M31) -> 1535.678
A32: SALE30 | B32: 45217 | C32: CUST1028 | D32: PROD5 | E32: STORE19 | F32: 1 | G32: =IF(F32="",M32/(I32*(1-J32)),F32) -> 1 | H32: 429.38 | I32: =IF(H32="",VLOOKUP($D32,Product_Dim_Cleaned!$A$2:$F$101,6,FALSE),H32) -> 429.38 | J32: 0.13 | K32: =IF(J32="",1-(M32/(G32*I32)),J32) -> 0.13 | L32: PayPal | M32: 373.5606 | N32: =IF(M32="",G32*I32*(1-K32),M32) -> 373.5606
A33: SALE31 | B33: 45593 | C33: CUST1412 | D33: PROD53 | E33: STORE12 | F33: 2 | G33: =IF(F33="",M33/(I33*(1-J33)),F33) -> 2 | H33: 148.96 | I33: =IF(H33="",VLOOKUP($D33,Product_Dim_Cleaned!$A$2:$F$101,6,FALSE),H33) -> 148.96 | J33: 0.03 | K33: =IF(J33="",1-(M33/(G33*I33)),J33) -> 0.03 | L33: COD | M33: 288.9824 | N33: =IF(M33="",G33*I33*(1-K33),M33) -> 288.9824
A34: SALE32 | B34: 45597 | C34: CUST1398 | D34: PROD75 | E34: STORE8 | F34: 4 | G34: =IF(F34="",M34/(I34*(1-J34)),F34) -> 4 | H34: 313.83 | I34: =IF(H34="",VLOOKUP($D34,Product_Dim_Cleaned!$A$2:$F$101,6,FALSE),H34) -> 313.83 | J34: 0.08 | K34: =IF(J34="",1-(M34/(G34*I34)),J34) -> 0.08 | L34: Credit Card | M34: 1154.8944 | N34: =IF(M34="",G34*I34*(1-K34),M34) -> 1154.8944
A35: SALE33 | B35: 45620 | C35: CUST1453 | D35: PROD12 | E35: STORE6 | F35: 2 | G35: =IF(F35="",M35/(I35*(1-J35)),F35) -> 2 | H35: 717.31 | I35: =IF(H35="",VLOOKUP($D35,Product_Dim_Cleaned!$A$2:$F$101,6,FALSE),H35) -> 717.31 | J35: 0.15 | K35: =IF(J35="",1-(M35/(G35*I35)),J35) -> 0.15 | L35: Credit Card | M35: 1219.427 | N35: =IF(M35="",G35*I35*(1-K35),M35) -> 1219.427
A36: SALE34 | B36: 45215 | C36: CUST1344 | D36: PROD79 | E36: STORE1 | G36: =IF(F36="",M36/(I36*(1-J36)),F36) -> 3 | H36: 873.22 | I36: =IF(H36="",VLOOKUP($D36,Product_Dim_Cleaned!$A$2:$F$101,6,FALSE),H36) -> 873.22 | J36: 0.18 | K36: =IF(J36="",1-(M36/(G36*I36)),J36) -> 0.18 | L36: Credit Card | M36: 2148.1212 | N36: =IF(M36="",G36*I36*(1-K36),M36) -> 2148.1212
A37: SALE35 | B37: 45878 | C37: CUST1218 | D37: PROD16 | E37: STORE3 | F37: 4 | G37: =IF(F37="",M37/(I37*(1-J37)),F37) -> 4 | H37: 109.36 | I37: =IF(H37="",VLOOKUP($D37,Product_Dim_Cleaned!$A$2:$F$101,6,FALSE),H37) -> 109.36 | J37: 0.19 | K37: =IF(J37="",1-(M37/(G37*I37)),J37) -> 0.19 | L37: COD | M37: 354.3264 | N37: =IF(M37="",G37*I37*(1-K37),M37) -> 354.3264
A38: SALE36 | B38: 45635 | C38: CUST1086 | D38: PROD5 | E38: STORE7 | F38: 3 | G38: =IF(F38="",M38/(I38*(1-J38)),F38) -> 3 | H38: 559.52 | I38: =IF(H38="",VLOOKUP($D38,Product_Dim_Cleaned!$A$2:$F$101,6,FALSE),H38) -> 559.52 | J38: 0.16 | K38: =IF(J38="",1-(M38/(G38*I38)),J38) -> 0.16 | L38: PayPal | M38: 1409.9904 | N38: =IF(M38="",G38*I38*(1-K38),M38) -> 1409.9904
A39: SALE37 | B39: 45329 | C39: CUST1492 | D39: PROD10 | E39: STORE17 | F39: 3 | G39: =IF(F39="",M39/(I39*(1-J39)),F39) -> 3 | H39: 121.76 | I39: =IF(H39="",VLOOKUP($D39,Product_Dim_Cleaned!$A$2:$F$101,6,FALSE),H39) -> 121.76 | J39: 0.27 | K39: =IF(J39="",1-(M39/(G39*I39)),J39) -> 0.27 | L39: PayPal | M39: 266.6544 | N39: =IF(M39="",G39*I39*(1-K39),M39) -> 266.6544
A40: SALE38 | B40: 45378 | C40: CUST1189 | D40: PROD33 | E40: STORE13 | F40: 4 | G40: =IF(F40="",M40/(I40*(1-J40)),F40) -> 4 | H40: 735.32 | I40: =IF(H40="",VLOOKUP($D40,Product_Dim_Cleaned!$A$2:$F$101,6,FALSE),H40) -> 735.32 | J40: 0.06 | K40: =IF(J40="",1-(M40/(G40*I40)),J40) -> 0.06 | L40: COD | M40: 2764.8032 | N40: =IF(M40="",G40*I40*(1-K40),M40) -> 2764.8032
A41: SALE39 | B41: 45264 | C41: CUST1431 | D41: PROD94 | E41: STORE3 | F41: 2 | G41: =IF(F41="",M41/(I41*(1-J41)),F41) -> 2 | H41: 600.73 | I41: =IF(H41="",VLOOKUP($D41,Product_Dim_Cleaned!$A$2:$F$101,6,FALSE),H41) -> 600.73 | J41: 0.08 | K41: =IF(J41="",1-(M41/(G41*I41)),J41) -> 0.08 | L41: Credit Card | M41: 1105.3432 | N41: =IF(M41="",G41*I41*(1-K41),M41) -> 1105.3432
A42: SALE40 | B42: 45486 | C42: CUST1072 | D42: PROD26 | E42: STORE19 | F42: 2 | G42: =IF(F42="",M42/(I42*(1-J42)),F42) -> 2 | H42: 873.86 | I42: =IF(H42="",VLOOKUP($D42,Product_Dim_Cleaned!$A$2:$F$101,6,FALSE),H42) -> 873.86 | J42: 0.07 | K42: =IF(J42="",1-(M42/(G42*I42)),J42) -> 0.07 | L42: COD | M42: 1625.3796 | N42: =IF(M42="",G42*I42*(1-K42),M42) -> 1625.3796
A43: SALE41 | B43: 45241 | C43: CUST1302 | D43: PROD23 | E43: STORE8 | F43: 3 | G43: =IF(F43="",M43/(I43*(1-J43)),F43) -> 3 | H43: 342.47 | I43: =IF(H43="",VLOOKUP($D43,Product_Dim_Cleaned!$A$2:$F$101,6,FALSE),H43) -> 342.47 | J43: 0.08 | K43: =IF(J43="",1-(M43/(G43*I43)),J43) -> 0.08 | L43: PayPal | M43: 945.2172 | N43: =IF(M43="",G43*I43*(1-K43),M43) -> 945.2172
A44: SALE42 | B44: 45649 | C44: CUST1335 | D44: PROD29 | E44: STORE9 | F44: 2 | G44: =IF(F44="",M44/(I44*(1-J44)),F44) -> 2 | H44: 915.15 | I44: =IF(H44="",VLOOKUP($D44,Product_Dim_Cleaned!$A$2:$F$101,6,FALSE),H44) -> 915.15 | J44: 0.16 | K44: =IF(J44="",1-(M44/(G44*I44)),J44) -> 0.16 | L44: PayPal | M44: 1537.452 | N44: =IF(M44="",G44*I44*(1-K44),M44) -> 1537.452
A45: SALE43 | B45: 45677 | C45: CUST1084 | D45: PROD33 | E45: STORE17 | G45: =IF(F45="",M45/(I45*(1-J45)),F45) -> 3 | H45: 863.11 | I45: =IF(H45="",VLOOKUP($D45,Product_Dim_Cleaned!$A$2:$F$101,6,FALSE),H45) -> 863.11 | J45: 0.28 | K45: =IF(J45="",1-(M45/(G45*I45)),J45) -> 0.28 | L45: PayPal | M45: 1864.3176 | N45: =IF(M45="",G45*I45*(1-K45),M45) -> 1864.3176
A46: SALE44 | B46: 45538 | C46: CUST1203 | D46: PROD43 | E46: STORE12 | F46: 2 | G46: =IF(F46="",M46/(I46*(1-J46)),F46) -> 2 | H46: 209.32 | I46: =IF(H46="",VLOOKUP($D46,Product_Dim_Cleaned!$A$2:$F$101,6,FALSE),H46) -> 209.32 | J46: 0.23 | K46: =IF(J46="",1-(M46/(G46*I46)),J46) -> 0.23 | L46: COD | M46: 322.3528 | N46: =IF(M46="",G46*I46*(1-K46),M46) -> 322.3528
A47: SALE45 | B47: 45606 | C47: CUST1470 | D47: PROD59 | E47: STORE8 | F47: 4 | G47: =IF(F47="",M47/(I47*(1-J47)),F47) -> 4 | H47: 288.6 | I47: =IF(H47="",VLOOKUP($D47,Product_Dim_Cleaned!$A$2:$F$101,6,FALSE),H47) -> 288.6 | J47: 0.09 | K47: =IF(J47="",1-(M47/(G47*I47)),J47) -> 0.09 | L47: PayPal | M47: 1050.504 | N47: =IF(M47="",G47*I47*(1-K47),M47) -> 1050.504
A48: SALE46 | B48: 45570 | C48: CUST1070 | D48: PROD78 | E48: STORE16 | F48: 1 | G48: =IF(F48="",M48/(I48*(1-J48)),F48) -> 1 | H48: 418.69 | I48: =IF(H48="",VLOOKUP($D48,Product_Dim_Cleaned!$A$2:$F$101,6,FALSE),H48) -> 418.69 | J48: 0.06 | K48: =IF(J48="",1-(M48/(G48*I48)),J48) -> 0.06 | L48: PayPal | M48: 393.5686 | N48: =IF(M48="",G48*I48*(1-K48),M48) -> 393.5686
A49: SALE47 | B49: 45466 | C49: CUST1008 | D49: PROD30 | E49: STORE11 | F49: 1 | G49: =IF(F49="",M49/(I49*(1-J49)),F49) -> 1 | H49: 135.78 | I49: =IF(H49="",VLOOKUP($D49,Product_Dim_Cleaned!$A$2:$F$101,6,FALSE),H49) -> 135.78 | J49: 0.14 | K49: =IF(J49="",1-(M49/(G49*I49)),J49) -> 0.14 | L49: PayPal | M49: 116.7708 | N49: =IF(M49="",G49*I49*(1-K49),M49) -> 116.7708
A50: SALE48 | B50: 45218 | C50: CUST1203 | D50: PROD44 | E50: STORE17 | F50: 1 | G50: =IF(F50="",M50/(I50*(1-J50)),F50) -> 1 | H50: 517.13 | I50: =IF(H50="",VLOOKUP($D50,Product_Dim_Cleaned!$A$2:$F$101,6,FALSE),H50) -> 517.13 | J50: 0.28 | K50: =IF(J50="",1-(M50/(G50*I50)),J50) -> 0.28 | L50: Credit Card | M50: 372.3336 | N50: =IF(M50="",G50*I50*(1-K50),M50) -> 372.3336
A51: SALE49 | B51: 45607 | C51: CUST1420 | D51: PROD21 | E51: STORE16 | F51: 2 | G51: =IF(F51="",M51/(I51*(1-J51)),F51) -> 2 | H51: 384.66 | I51: =IF(H51="",VLOOKUP($D51,Product_Dim_Cleaned!$A$2:$F$101,6,FALSE),H51) -> 384.66 | J51: 0.08 | K51: =IF(J51="",1-(M51/(G51*I51)),J51) -> 0.08 | L51: COD | M51: 707.7744 | N51: =IF(M51="",G51*I51*(1-K51),M51) -> 707.7744
A52: SALE50 | B52: 45291 | C52: CUST1070 | D52: PROD52 | E52: STORE9 | F52: 3 | G52: =IF(F52="",M52/(I52*(1-J52)),F52) -> 3 | H52: 83.7 | I52: =IF(H52="",VLOOKUP($D52,Product_Dim_Cleaned!$A$2:$F$101,6,FALSE),H52) -> 83.7 | J52: 0.24 | K52: =IF(J52="",1-(M52/(G52*I52)),J52) -> 0.24 | L52: PayPal | M52: 190.836 | N52: =IF(M52="",G52*I52*(1-K52),M52) -> 190.836
A53: SALE51 | B53: 45689 | C53: CUST1142 | D53: PROD69 | E53: STORE7 | F53: 3 | G53: =IF(F53="",M53/(I53*(1-J53)),F53) -> 3 | H53: 76.57 | I53: =IF(H53="",VLOOKUP($D53,Product_Dim_Cleaned!$A$2:$F$101,6,FALSE),H53) -> 76.57 | J53: 0.26 | K53: =IF(J53="",1-(M53/(G53*I53)),J53) -> 0.26 | L53: Credit Card | M53: 169.9854 | N53: =IF(M53="",G53*I53*(1-K53),M53) -> 169.9854
A54: SALE52 | B54: 45894 | C54: CUST1148 | D54: PROD89 | E54: STORE6 | F54: 3 | G54: =IF(F54="",M54/(I54*(1-J54)),F54) -> 3 | I54: =IF(H54="",VLOOKUP($D54,Product_Dim_Cleaned!$A$2:$F$101,6,FALSE),H54) -> 183.04 | K54: =IF(J54="",1-(M54/(G54*I54)),J54) -> 0.11483228 | L54: Credit Card | M54: 486.0633 | N54: =IF(M54="",G54*I54*(1-K54),M54) -> 486.0633
A55: SALE53 | B55: 45677 | C55: CUST1324 | D55: PROD20 | E55: STORE8 | F55: 1 | G55: =IF(F55="",M55/(I55*(1-J55)),F55) -> 1 | H55: 900.35 | I55: =IF(H55="",VLOOKUP($D55,Product_Dim_Cleaned!$A$2:$F$101,6,FALSE),H55) -> 900.35 | J55: 0.13 | K55: =IF(J55="",1-(M55/(G55*I55)),J55) -> 0.13 | L55: COD | M55: 783.3045 | N55: =IF(M55="",G55*I55*(1-K55),M55) -> 783.3045
A56: SALE54 | B56: 45706 | C56: CUST1095 | D56: PROD40 | E56: STORE10 | F56: 4 | G56: =IF(F56="",M56/(I56*(1-J56)),F56) -> 4 | H56: 428.09 | I56: =IF(H56="",VLOOKUP($D56,Product_Dim_Cleaned!$A$2:$F$101,6,FALSE),H56) -> 428.09 | J56: 0.07 | K56: =IF(J56="",1-(M56/(G56*I56)),J56) -> 0.07 | L56: Credit Card | M56: 1592.4948 | N56: =IF(M56="",G56*I56*(1-K56),M56) -> 1592.4948
A57: SALE55 | B57: 45589 | C57: CUST1416 | D57: PROD49 | E57: STORE11 | F57: 2 | G57: =IF(F57="",M57/(I57*(1-J57)),F57) -> 2 | H57: 559.71 | I57: =IF(H57="",VLOOKUP($D57,Product_Dim_Cleaned!$A$2:$F$101,6,FALSE),H57) -> 559.71 | J57: 0.3 | K57: =IF(J57="",1-(M57/(G57*I57)),J57) -> 0.3 | L57: COD | M57: 783.594 | N57: =IF(M57="",G57*I57*(1-K57),M57) -> 783.594
A58: SALE56 | B58: 45282 | C58: CUST1080 | D58: PROD34 | E58: STORE6 | F58: 2 | G58: =IF(F58="",M58/(I58*(1-J58)),F58) -> 2 | H58: 833.7 | I58: =IF(H58="",VLOOKUP($D58,Product_Dim_Cleaned!$A$2:$F$101,6,FALSE),H58) -> 833.7 | J58: 0.06 | K58: =IF(J58="",1-(M58/(G58*I58)),J58) -> 0.06 | L58: PayPal | M58: 1567.356 | N58: =IF(M58="",G58*I58*(1-K58),M58) -> 1567.356
A59: SALE57 | B59: 45462 | C59: CUST1467 | D59: PROD47 | E59: STORE14 | F59: 2 | G59: =IF(F59="",M59/(I59*(1-J59)),F59) -> 2 | H59: 680.16 | I59: =IF(H59="",VLOOKUP($D59,Product_Dim_Cleaned!$A$2:$F$101,6,FALSE),H59) -> 680.16 | J59: 0.28 | K59: =IF(J59="",1-(M59/(G59*I59)),J59) -> 0.28 | L59: Credit Card | M59: 979.4304 | N59: =IF(M59="",G59*I59*(1-K59),M59) -> 979.4304
A60: SALE58 | B60: 45633 | C60: CUST1404 | D60: PROD15 | E60: STORE7 | F60: 4 | G60: =IF(F60="",M60/(I60*(1-J60)),F60) -> 4 | H60: 733.42 | I60: =IF(H60="",VLOOKUP($D60,Product_Dim_Cleaned!$A$2:$F$101,6,FALSE),H60) -> 733.42 | K60: =IF(J60="",1-(M60/(G60*I60)),J60) -> 0.13 | L60: PayPal | M60: 2552.3016 | N60: =IF(M60="",G60*I60*(1-K60),M60) -> 2552.3016
A61: SALE59 | B61: 45257 | C61: CUST1367 | D61: PROD89 | E61: STORE11 | F61: 1 | G61: =IF(F61="",M61/(I61*(1-J61)),F61) -> 1 | H61: 996.33 | I61: =IF(H61="",VLOOKUP($D61,Product_Dim_Cleaned!$A$2:$F$101,6,FALSE),H61) -> 996.33 | J61: 0.23 | K61: =IF(J61="",1-(M61/(G61*I61)),J61) -> 0.23 | L61: PayPal | M61: 767.1741 | N61: =IF(M61="",G61*I61*(1-K61),M61) -> 767.1741
A62: SALE60 | B62: 45854 | C62: CUST1408 | D62: PROD31 | E62: STORE10 | F62: 1 | G62: =IF(F62="",M62/(I62*(1-J62)),F62) -> 1 | H62: 198.83 | I62: =IF(H62="",VLOOKUP($D62,Product_Dim_Cleaned!$A$2:$F$101,6,FALSE),H62) -> 198.83 | J62: 0.09 | K62: =IF(J62="",1-(M62/(G62*I62)),J62) -> 0.09 | L62: COD | M62: 180.9353 | N62: =IF(M62="",G62*I62*(1-K62),M62) -> 180.9353
A63: SALE61 | B63: 45716 | C63: CUST1239 | D63: PROD19 | E63: STORE7 | F63: 1 | G63: =IF(F63="",M63/(I63*(1-J63)),F63) -> 1 | H63: 374.92 | I63: =IF(H63="",VLOOKUP($D63,Product_Dim_Cleaned!$A$2:$F$101,6,FALSE),H63) -> 374.92 | J63: 0.18 | K63: =IF(J63="",1-(M63/(G63*I63)),J63) -> 0.18 | L63: PayPal | M63: 307.4344 | N63: =IF(M63="",G63*I63*(1-K63),M63) -> 307.4344
A64: SALE62 | B64: 45515 | C64: CUST1464 | D64: PROD93 | E64: STORE16 | F64: 1 | G64: =IF(F64="",M64/(I64*(1-J64)),F64) -> 1 | H64: 468.94 | I64: =IF(H64="",VLOOKUP($D64,Product_Dim_Cleaned!$A$2:$F$101,6,FALSE),H64) -> 468.94 | J64: 0.12 | K64: =IF(J64="",1-(M64/(G64*I64)),J64) -> 0.12 | L64: Credit Card | M64: 412.6672 | N64: =IF(M64="",G64*I64*(1-K64),M64) -> 412.6672
A65: SALE63 | B65: 45927 | C65: CUST1126 | D65: PROD89 | E65: STORE12 | F65: 2 | G65: =IF(F65="",M65/(I65*(1-J65)),F65) -> 2 | H65: 121.37 | I65: =IF(H65="",VLOOKUP($D65,Product_Dim_Cleaned!$A$2:$F$101,6,FALSE),H65) -> 121.37 | J65: 0.05 | K65: =IF(J65="",1-(M65/(G65*I65)),J65) -> 0.05 | L65: Credit Card | M65: 230.603 | N65: =IF(M65="",G65*I65*(1-K65),M65) -> 230.603
A66: SALE64 | B66: 45914 | C66: CUST1255 | D66: PROD53 | E66: STORE10 | F66: 3 | G66: =IF(F66="",M66/(I66*(1-J66)),F66) -> 3 | H66: 480.06 | I66: =IF(H66="",VLOOKUP($D66,Product_Dim_Cleaned!$A$2:$F$101,6,FALSE),H66) -> 480.06 | J66: 0.01 | K66: =IF(J66="",1-(M66/(G66*I66)),J66) -> 0.01 | L66: Credit Card | N66: =IF(M66="",G66*I66*(1-K66),M66) -> 1425.7782
A67: SALE65 | B67: 45290 | C67: CUST1162 | D67: PROD99 | E67: STORE17 | F67: 2 | G67: =IF(F67="",M67/(I67*(1-J67)),F67) -> 2 | H67: 856.57 | I67: =IF(H67="",VLOOKUP($D67,Product_Dim_Cleaned!$A$2:$F$101,6,FALSE),H67) -> 856.57 | J67: 0.24 | K67: =IF(J67="",1-(M67/(G67*I67)),J67) -> 0.24 | L67: Credit Card | M67: 1301.9864 | N67: =IF(M67="",G67*I67*(1-K67),M67) -> 1301.9864
A68: SALE66 | B68: 45213 | C68: CUST1269 | D68: PROD77 | E68: STORE2 | F68: 4 | G68: =IF(F68="",M68/(I68*(1-J68)),F68) -> 4 | H68: 814.25 | I68: =IF(H68="",VLOOKUP($D68,Product_Dim_Cleaned!$A$2:$F$101,6,FALSE),H68) -> 814.25 | J68: 0.18 | K68: =IF(J68="",1-(M68/(G68*I68)),J68) -> 0.18 | L68: Credit Card | M68: 2670.74 | N68: =IF(M68="",G68*I68*(1-K68),M68) -> 2670.74
A69: SALE67 | B69: 45255 | C69: CUST1483 | D69: PROD12 | E69: STORE2 | F69: 1 | G69: =IF(F69="",M69/(I69*(1-J69)),F69) -> 1 | H69: 989.17 | I69: =IF(H69="",VLOOKUP($D69,Product_Dim_Cleaned!$A$2:$F$101,6,FALSE),H69) -> 989.17 | J69: 0.2 | K69: =IF(J69="",1-(M69/(G69*I69)),J69) -> 0.2 | L69: PayPal | M69: 791.336 | N69: =IF(M69="",G69*I69*(1-K69),M69) -> 791.336
A70: SALE68 | B70: 45270 | C70: CUST1372 | D70: PROD72 | E70: STORE10 | F70: 4 | G70: =IF(F70="",M70/(I70*(1-J70)),F70) -> 4 | H70: 62.48 | I70: =IF(H70="",VLOOKUP($D70,Product_Dim_Cleaned!$A$2:$F$101,6,FALSE),H70) -> 62.48 | J70: 0.18 | K70: =IF(J70="",1-(M70/(G70*I70)),J70) -> 0.18 | L70: Credit Card | M70: 204.9344 | N70: =IF(M70="",G70*I70*(1-K70),M70) -> 204.9344
A71: SALE69 | B71: 45897 | C71: CUST1423 | D71: PROD13 | E71: STORE16 | F71: 4 | G71: =IF(F71="",M71/(I71*(1-J71)),F71) -> 4 | H71: 561.24 | I71: =IF(H71="",VLOOKUP($D71,Product_Dim_Cleaned!$A$2:$F$101,6,FALSE),H71) -> 561.24 | J71: 0.24 | K71: =IF(J71="",1-(M71/(G71*I71)),J71) -> 0.24 | L71: Credit Card | M71: 1706.1696 | N71: =IF(M71="",G71*I71*(1-K71),M71) -> 1706.1696
A72: SALE70 | B72: 45849 | C72: CUST1058 | D72: PROD60 | E72: STORE5 | F72: 3 | G72: =IF(F72="",M72/(I72*(1-J72)),F72) -> 3 | H72: 92.24 | I72: =IF(H72="",VLOOKUP($D72,Product_Dim_Cleaned!$A$2:$F$101,6,FALSE),H72) -> 92.24 | J72: 0.28 | K72: =IF(J72="",1-(M72/(G72*I72)),J72) -> 0.28 | L72: COD | N72: =IF(M72="",G72*I72*(1-K72),M72) -> 199.2384
A73: SALE71 | B73: 45889 | C73: CUST1168 | D73: PROD72 | E73: STORE1 | F73: 2 | G73: =IF(F73="",M73/(I73*(1-J73)),F73) -> 2 | H73: 668.3 | I73: =IF(H73="",VLOOKUP($D73,Product_Dim_Cleaned!$A$2:$F$101,6,FALSE),H73) -> 668.3 | J73: 0.07 | K73: =IF(J73="",1-(M73/(G73*I73)),J73) -> 0.07 | L73: Credit Card | M73: 1243.038 | N73: =IF(M73="",G73*I73*(1-K73),M73) -> 1243.038
A74: SALE72 | B74: 45533 | C74: CUST1409 | D74: PROD38 | E74: STORE5 | F74: 1 | G74: =IF(F74="",M74/(I74*(1-J74)),F74) -> 1 | H74: 553.82 | I74: =IF(H74="",VLOOKUP($D74,Product_Dim_Cleaned!$A$2:$F$101,6,FALSE),H74) -> 553.82 | J74: 0.09 | K74: =IF(J74="",1-(M74/(G74*I74)),J74) -> 0.09 | L74: Credit Card | M74: 503.9762 | N74: =IF(M74="",G74*I74*(1-K74),M74) -> 503.9762
A75: SALE73 | B75: 45626 | C75: CUST1037 | D75: PROD45 | E75: STORE11 | F75: 2 | G75: =IF(F75="",M75/(I75*(1-J75)),F75) -> 2 | H75: 556.43 | I75: =IF(H75="",VLOOKUP($D75,Product_Dim_Cleaned!$A$2:$F$101,6,FALSE),H75) -> 556.43 | J75: 0.13 | K75: =IF(J75="",1-(M75/(G75*I75)),J75) -> 0.13 | L75: Credit Card | M75: 968.1882 | N75: =IF(M75="",G75*I75*(1-K75),M75) -> 968.1882
A76: SALE74 | B76: 45942 | C76: CUST1273 | D76: PROD20 | E76: STORE8 | F76: 1 | G76: =IF(F76="",M76/(I76*(1-J76)),F76) -> 1 | H76: 184.98 | I76: =IF(H76="",VLOOKUP($D76,Product_Dim_Cleaned!$A$2:$F$101,6,FALSE),H76) -> 184.98 | J76: 0.1 | K76: =IF(J76="",1-(M76/(G76*I76)),J76) -> 0.1 | L76: COD | M76: 166.482 | N76: =IF(M76="",G76*I76*(1-K76),M76) -> 166.482
A77: SALE75 | B77: 45500 | C77: CUST1035 | D77: PROD97 | E77: STORE12 | F77: 4 | G77: =IF(F77="",M77/(I77*(1-J77)),F77) -> 4 | H77: 700.18 | I77: =IF(H77="",VLOOKUP($D77,Product_Dim_Cleaned!$A$2:$F$101,6,FALSE),H77) -> 700.18 | J77: 0.23 | K77: =IF(J77="",1-(M77/(G77*I77)),J77) -> 0.23 | L77: Credit Card | M77: 2156.5544 | N77: =IF(M77="",G77*I77*(1-K77),M77) -> 2156.5544
A78: SALE76 | B78: 45285 | C78: CUST1019 | D78: PROD76 | E78: STORE10 | F78: 2 | G78: =IF(F78="",M78/(I78*(1-J78)),F78) -> 2 | H78: 686.31 | I78: =IF(H78="",VLOOKUP($D78,Product_Dim_Cleaned!$A$2:$F$101,6,FALSE),H78) -> 686.31 | J78: 0.25 | K78: =IF(J78="",1-(M78/(G78*I78)),J78) -> 0.25 | L78: Credit Card | M78: 1029.465 | N78: =IF(M78="",G78*I78*(1-K78),M78) -> 1029.465
A79: SALE77 | B79: 45800 | C79: CUST1007 | D79: PROD67 | E79: STORE15 | F79: 1 | G79: =IF(F79="",M79/(I79*(1-J79)),F79) -> 1 | H79: 687.82 | I79: =IF(H79="",VLOOKUP($D79,Product_Dim_Cleaned!$A$2:$F$101,6,FALSE),H79) -> 687.82 | J79: 0.27 | K79: =IF(J79="",1-(M79/(G79*I79)),J79) -> 0.27 | L79: COD | M79: 502.1086 | N79: =IF(M79="",G79*I79*(1-K79),M79) -> 502.1086
A80: SALE78 | B80: 45609 | C80: CUST1221 | D80: PROD83 | E80: STORE8 | F80: 2 | G80: =IF(F80="",M80/(I80*(1-J80)),F80) -> 2 | H80: 900.55 | I80: =IF(H80="",VLOOKUP($D80,Product_Dim_Cleaned!$A$2:$F$101,6,FALSE),H80) -> 900.55 | J80: 0.16 | K80: =IF(J80="",1-(M80/(G80*I80)),J80) -> 0.16 | L80: Credit Card | M80: 1512.924 | N80: =IF(M80="",G80*I80*(1-K80),M80) -> 1512.924
A81: SALE79 | B81: 45268 | C81: CUST1115 | D81: PROD21 | E81: STORE2 | F81: 1 | G81: =IF(F81="",M81/(I81*(1-J81)),F81) -> 1 | H81: 341.17 | I81: =IF(H81="",VLOOKUP($D81,Product_Dim_Cleaned!$A$2:$F$101,6,FALSE),H81) -> 341.17 | J81: 0.15 | K81: =IF(J81="",1-(M81/(G81*I81)),J81) -> 0.15 | L81: Credit Card | M81: 289.9945 | N81: =IF(M81="",G81*I81*(1-K81),M81) -> 289.9945
A82: SALE80 | B82: 45885 | C82: CUST1176 | D82: PROD52 | E82: STORE8 | F82: 1 | G82: =IF(F82="",M82/(I82*(1-J82)),F82) -> 1 | H82: 442.27 | I82: =IF(H82="",VLOOKUP($D82,Product_Dim_Cleaned!$A$2:$F$101,6,FALSE),H82) -> 442.27 | J82: 0.06 | K82: =IF(J82="",1-(M82/(G82*I82)),J82) -> 0.06 | L82: COD | M82: 415.7338 | N82: =IF(M82="",G82*I82*(1-K82),M82) -> 415.7338
A83: SALE81 | B83: 45616 | C83: CUST1253 | D83: PROD71 | E83: STORE9 | F83: 1 | G83: =IF(F83="",M83/(I83*(1-J83)),F83) -> 1 | H83: 363.73 | I83: =IF(H83="",VLOOKUP($D83,Product_Dim_Cleaned!$A$2:$F$101,6,FALSE),H83) -> 363.73 | J83: 0.25 | K83: =IF(J83="",1-(M83/(G83*I83)),J83) -> 0.25 | L83: PayPal | M83: 272.7975 | N83: =IF(M83="",G83*I83*(1-K83),M83) -> 272.7975
A84: SALE82 | B84: 45518 | C84: CUST1378 | D84: PROD91 | E84: STORE17 | F84: 2 | G84: =IF(F84="",M84/(I84*(1-J84)),F84) -> 2 | H84: 601.33 | I84: =IF(H84="",VLOOKUP($D84,Product_Dim_Cleaned!$A$2:$F$101,6,FALSE),H84) -> 601.33 | J84: 0.16 | K84: =IF(J84="",1-(M84/(G84*I84)),J84) -> 0.16 | L84: PayPal | M84: 1010.2344 | N84: =IF(M84="",G84*I84*(1-K84),M84) -> 1010.2344
A85: SALE83 | B85: 45427 | C85: CUST1403 | D85: PROD17 | E85: STORE18 | F85: 4 | G85: =IF(F85="",M85/(I85*(1-J85)),F85) -> 4 | H85: 34.39 | I85: =IF(H85="",VLOOKUP($D85,Product_Dim_Cleaned!$A$2:$F$101,6,FALSE),H85) -> 34.39 | J85: 0.03 | K85: =IF(J85="",1-(M85/(G85*I85)),J85) -> 0.03 | L85: PayPal | M85: 133.4332 | N85: =IF(M85="",G85*I85*(1-K85),M85) -> 133.4332
A86: SALE84 | B86: 45268 | C86: CUST1423 | D86: PROD46 | E86: STORE17 | F86: 1 | G86: =IF(F86="",M86/(I86*(1-J86)),F86) -> 1 | H86: 773.57 | I86: =IF(H86="",VLOOKUP($D86,Product_Dim_Cleaned!$A$2:$F$101,6,FALSE),H86) -> 773.57 | J86: 0.05 | K86: =IF(J86="",1-(M86/(G86*I86)),J86) -> 0.05 | L86: COD | N86: =IF(M86="",G86*I86*(1-K86),M86) -> 734.8915
A87: SALE85 | B87: 45282 | C87: CUST1054 | D87: PROD88 | E87: STORE7 | F87: 4 | G87: =IF(F87="",M87/(I87*(1-J87)),F87) -> 4 | H87: 127.1 | I87: =IF(H87="",VLOOKUP($D87,Product_Dim_Cleaned!$A$2:$F$101,6,FALSE),H87) -> 127.1 | J87: 0.24 | K87: =IF(J87="",1-(M87/(G87*I87)),J87) -> 0.24 | L87: COD | M87: 386.384 | N87: =IF(M87="",G87*I87*(1-K87),M87) -> 386.384
A88: SALE86 | B88: 45545 | C88: CUST1303 | D88: PROD20 | E88: STORE3 | F88: 3 | G88: =IF(F88="",M88/(I88*(1-J88)),F88) -> 3 | H88: 899.58 | I88: =IF(H88="",VLOOKUP($D88,Product_Dim_Cleaned!$A$2:$F$101,6,FALSE),H88) -> 899.58 | J88: 0.28 | K88: =IF(J88="",1-(M88/(G88*I88)),J88) -> 0.28 | L88: PayPal | M88: 1943.0928 | N88: =IF(M88="",G88*I88*(1-K88),M88) -> 1943.0928
A89: SALE87 | B89: 45755 | C89: CUST1327 | D89: PROD1 | E89: STORE10 | F89: 3 | G89: =IF(F89="",M89/(I89*(1-J89)),F89) -> 3 | H89: 964.39 | I89: =IF(H89="",VLOOKUP($D89,Product_Dim_Cleaned!$A$2:$F$101,6,FALSE),H89) -> 964.39 | J89: 0.04 | K89: =IF(J89="",1-(M89/(G89*I89)),J89) -> 0.04 | L89: Credit Card | M89: 2777.4432 | N89: =IF(M89="",G89*I89*(1-K89),M89) -> 2777.4432
A90: SALE88 | B90: 45588 | C90: CUST1183 | D90: PROD38 | E90: STORE0 | F90: 2 | G90: =IF(F90="",M90/(I90*(1-J90)),F90) -> 2 | H90: 217.83 | I90: =IF(H90="",VLOOKUP($D90,Product_Dim_Cleaned!$A$2:$F$101,6,FALSE),H90) -> 217.83 | J90: 0.14 | K90: =IF(J90="",1-(M90/(G90*I90)),J90) -> 0.14 | L90: PayPal | M90: 374.6676 | N90: =IF(M90="",G90*I90*(1-K90),M90) -> 374.6676
A91: SALE89 | B91: 45848 | C91: CUST1143 | D91: PROD17 | E91: STORE1 | F91: 4 | G91: =IF(F91="",M91/(I91*(1-J91)),F91) -> 4 | H91: 187.71 | I91: =IF(H91="",VLOOKUP($D91,Product_Dim_Cleaned!$A$2:$F$101,6,FALSE),H91) -> 187.71 | J91: 0.06 | K91: =IF(J91="",1-(M91/(G91*I91)),J91) -> 0.06 | L91: COD | M91: 705.7896 | N91: =IF(M91="",G91*I91*(1-K91),M91) -> 705.7896
A92: SALE90 | B92: 45577 | C92: CUST1010 | D92: PROD33 | E92: STORE18 | F92: 2 | G92: =IF(F92="",M92/(I92*(1-J92)),F92) -> 2 | H92: 350.12 | I92: =IF(H92="",VLOOKUP($D92,Product_Dim_Cleaned!$A$2:$F$101,6,FALSE),H92) -> 350.12 | J92: 0.12 | K92: =IF(J92="",1-(M92/(G92*I92)),J92) -> 0.12 | L92: COD | M92: 616.2112 | N92: =IF(M92="",G92*I92*(1-K92),M92) -> 616.2112
A93: SALE91 | B93: 45312 | C93: CUST1406 | D93: PROD16 | E93: STORE1 | F93: 4 | G93: =IF(F93="",M93/(I93*(1-J93)),F93) -> 4 | H93: 102.19 | I93: =IF(H93="",VLOOKUP($D93,Product_Dim_Cleaned!$A$2:$F$101,6,FALSE),H93) -> 102.19 | J93: 0.17 | K93: =IF(J93="",1-(M93/(G93*I93)),J93) -> 0.17 | L93: PayPal | M93: 339.2708 | N93: =IF(M93="",G93*I93*(1-K93),M93) -> 339.2708
A94: SALE92 | B94: 45350 | C94: CUST1007 | D94: PROD86 | E94: STORE4 | F94: 1 | G94: =IF(F94="",M94/(I94*(1-J94)),F94) -> 1 | H94: 696.53 | I94: =IF(H94="",VLOOKUP($D94,Product_Dim_Cleaned!$A$2:$F$101,6,FALSE),H94) -> 696.53 | J94: 0.17 | K94: =IF(J94="",1-(M94/(G94*I94)),J94) -> 0.17 | L94: Credit Card | M94: 578.1199 | N94: =IF(M94="",G94*I94*(1-K94),M94) -> 578.1199
A95: SALE93 | B95: 45657 | C95: CUST1065 | D95: PROD19 | E95: STORE4 | F95: 2 | G95: =IF(F95="",M95/(I95*(1-J95)),F95) -> 2 | H95: 327.52 | I95: =IF(H95="",VLOOKUP($D95,Product_Dim_Cleaned!$A$2:$F$101,6,FALSE),H95) -> 327.52 | J95: 0.15 | K95: =IF(J95="",1-(M95/(G95*I95)),J95) -> 0.15 | L95: PayPal | M95: 556.784 | N95: =IF(M95="",G95*I95*(1-K95),M95) -> 556.784
A96: SALE94 | B96: 45530 | C96: CUST1298 | D96: PROD97 | E96: STORE19 | F96: 2 | G96: =IF(F96="",M96/(I96*(1-J96)),F96) -> 2 | H96: 569.36 | I96: =IF(H96="",VLOOKUP($D96,Product_Dim_Cleaned!$A$2:$F$101,6,FALSE),H96) -> 569.36 | J96: 0.01 | K96: =IF(J96="",1-(M96/(G96*I96)),J96) -> 0.01 | L96: PayPal | N96: =IF(M96="",G96*I96*(1-K96),M96) -> 1127.3328
A97: SALE95 | B97: 45556 | C97: CUST1321 | D97: PROD99 | E97: STORE6 | F97: 2 | G97: =IF(F97="",M97/(I97*(1-J97)),F97) -> 2 | H97: 68.29 | I97: =IF(H97="",VLOOKUP($D97,Product_Dim_Cleaned!$A$2:$F$101,6,FALSE),H97) -> 68.29 | J97: 0.14 | K97: =IF(J97="",1-(M97/(G97*I97)),J97) -> 0.14 | L97: COD | M97: 117.4588 | N97: =IF(M97="",G97*I97*(1-K97),M97) -> 117.4588
A98: SALE96 | B98: 45523 | C98: CUST1244 | D98: PROD50 | E98: STORE10 | F98: 1 | G98: =IF(F98="",M98/(I98*(1-J98)),F98) -> 1 | H98: 842.9 | I98: =IF(H98="",VLOOKUP($D98,Product_Dim_Cleaned!$A$2:$F$101,6,FALSE),H98) -> 842.9 | J98: 0.06 | K98: =IF(J98="",1-(M98/(G98*I98)),J98) -> 0.06 | L98: COD | M98: 792.326 | N98: =IF(M98="",G98*I98*(1-K98),M98) -> 792.326
A99: SALE97 | B99: 45587 | C99: CUST1287 | D99: PROD3 | E99: STORE3 | F99: 3 | G99: =IF(F99="",M99/(I99*(1-J99)),F99) -> 3 | H99: 751.94 | I99: =IF(H99="",VLOOKUP($D99,Product_Dim_Cleaned!$A$2:$F$101,6,FALSE),H99) -> 751.94 | J99: 0.26 | K99: =IF(J99="",1-(M99/(G99*I99)),J99) -> 0.26 | L99: PayPal | M99: 1669.3068 | N99: =IF(M99="",G99*I99*(1-K99),M99) -> 1669.3068
A100: SALE98 | B100: 45580 | C100: CUST1131 | D100: PROD56 | E100: STORE7 | F100: 4 | G100: =IF(F100="",M100/(I100*(1-J100)),F100) -> 4 | H100: 476.28 | I100: =IF(H100="",VLOOKUP($D100,Product_Dim_Cleaned!$A$2:$F$101,6,FALSE),H100) -> 476.28 | J100: 0.17 | K100: =IF(J100="",1-(M100/(G100*I100)),J100) -> 0.17 | L100: Credit Card | M100: 1581.2496 | N100: =IF(M100="",G100*I100*(1-K100),M100) -> 1581.2496
...

Sheet Sales_Fact_Cleaned
A1: Sales_ID | B1: Order_Date | C1: Customer_ID | D1: Product_ID | E1: Store_ID | F1: Quantity | G1: Unit_Price | H1: Discount | I1: Payment_Type | J1: Total_Amount | K1: Customer_Name | L1: Product_Name | M1: Store_Name
A2: SALE0 | B2: 45480 | C2: CUST1409 | D2: PROD97 | E2: STORE3 | F2: 1 | G2: 245.98 | H2: 0.09 | I2: Credit Card | J2: 198.4164 | K2: =VLOOKUP($C2,Customer_Dim_Cleaned!$A$2:$H$501,2,FALSE) -> Sarah Smith | L2: =VLOOKUP($D2,Product_Dim_Cleaned!$A$2:$F$101,2,FALSE) -> Cricket Bat | M2: =VLOOKUP($E2,Store_Dim_Cleaned!$A$2:$E$21,2,FALSE) -> Johnson-Wright
A3: SALE1 | B3: 45285 | C3: CUST1467 | D3: PROD74 | E3: STORE17 | F3: 3 | G3: 104.47 | H3: 0.27 | I3: PayPal | J3: 228.7893 | K3: =VLOOKUP($C3,Customer_Dim_Cleaned!$A$2:$H$501,2,FALSE) -> Michael Foley | L3: =VLOOKUP($D3,Product_Dim_Cleaned!$A$2:$F$101,2,FALSE) -> Bluetooth Car Audio System | M3: =VLOOKUP($E3,Store_Dim_Cleaned!$A$2:$E$21,2,FALSE) -> Holloway Ltd
A4: SALE2 | B4: 45446 | C4: CUST1056 | D4: PROD49 | E4: STORE8 | F4: 4 | G4: 914.05 | H4: 0.25 | I4: Credit Card | J4: 2742.15 | K4: =VLOOKUP($C4,Customer_Dim_Cleaned!$A$2:$H$501,2,FALSE) -> Christopher Sutton | L4: =VLOOKUP($D4,Product_Dim_Cleaned!$A$2:$F$101,2,FALSE) -> Men's Roll-On Perfume | M4: =VLOOKUP($E4,Store_Dim_Cleaned!$A$2:$E$21,2,FALSE) -> Bean, Jones and Park
A5: SALE3 | B5: 45259 | C5: CUST1346 | D5: PROD76 | E5: STORE8 | F5: 1 | G5: 921.51 | H5: 0.16 | I5: COD | J5: 774.0684 | K5: =VLOOKUP($C5,Customer_Dim_Cleaned!$A$2:$H$501,2,FALSE) -> John Jordan | L5: =VLOOKUP($D5,Product_Dim_Cleaned!$A$2:$F$101,2,FALSE) -> Wireless Mouse | M5: =VLOOKUP($E5,Store_Dim_Cleaned!$A$2:$E$21,2,FALSE) -> Bean, Jones and Park
A6: SALE4 | B6: 45297 | C6: CUST1493 | D6: PROD59 | E6: STORE5 | F6: 3 | G6: 745.3 | H6: 0.18 | I6: Credit Card | J6: 1833.438 | K6: =VLOOKUP($C6,Customer_Dim_Cleaned!$A$2:$H$501,2,FALSE) -> Amanda Powell | L6: =VLOOKUP($D6,Product_Dim_Cleaned!$A$2:$F$101,2,FALSE) -> Men's Hair Styling Gel | M6: =VLOOKUP($E6,Store_Dim_Cleaned!$A$2:$E$21,2,FALSE) -> Gray Ltd
A7: SALE5 | B7: 45499 | C7: CUST1116 | D7: PROD15 | E7: STORE7 | F7: 3 | G7: 147.01 | H7: 0.19 | I7: COD | J7: 357.2343 | K7: =VLOOKUP($C7,Customer_Dim_Cleaned!$A$2:$H$501,2,FALSE) -> Anthony Phillips | L7: =VLOOKUP($D7,Product_Dim_Cleaned!$A$2:$F$101,2,FALSE) -> 4K Home Projector | M7: =VLOOKUP($E7,Store_Dim_Cleaned!$A$2:$E$21,2,FALSE) -> Martinez-Mullins
A8: SALE6 | B8: 45850 | C8: CUST1016 | D8: PROD56 | E8: STORE4 | F8: 2 | G8: 785.31 | H8: 0.15 | I8: PayPal | J8: 1335.027 | K8: =VLOOKUP($C8,Customer_Dim_Cleaned!$A$2:$H$501,2,FALSE) -> John Scott | L8: =VLOOKUP($D8,Product_Dim_Cleaned!$A$2:$F$101,2,FALSE) -> Premium Blanket Throw | M8: =VLOOKUP($E8,Store_Dim_Cleaned!$A$2:$E$21,2,FALSE) -> Alexander Group
A9: SALE7 | B9: 45248 | C9: CUST1152 | D9: PROD70 | E9: STORE8 | F9: 4 | G9: 342.39 | H9: 0.23 | I9: PayPal | J9: 1054.5612 | K9: =VLOOKUP($C9,Customer_Dim_Cleaned!$A$2:$H$501,2,FALSE) -> Patrick Roberts | L9: =VLOOKUP($D9,Product_Dim_Cleaned!$A$2:$F$101,2,FALSE) -> Kitchen Storage Rack | M9: =VLOOKUP($E9,Store_Dim_Cleaned!$A$2:$E$21,2,FALSE) -> Bean, Jones and Park
A10: SALE8 | B10: 45781 | C10: CUST1187 | D10: PROD99 | E10: STORE5 | F10: 3 | G10: 448.25 | H10: 0.07 | I10: PayPal | J10: 1250.6175 | K10: =VLOOKUP($C10,Customer_Dim_Cleaned!$A$2:$H$501,2,FALSE) -> Dr. Suzanne Bullock | L10: =VLOOKUP($D10,Product_Dim_Cleaned!$A$2:$F$101,2,FALSE) -> Stainless Steel Cookware Set | M10: =VLOOKUP($E10,Store_Dim_Cleaned!$A$2:$E$21,2,FALSE) -> Gray Ltd
A11: SALE9 | B11: 45869 | C11: CUST1464 | D11: PROD33 | E11: STORE0 | F11: 2 | G11: 873.17 | H11: 0.23 | I11: PayPal | J11: 1344.6818 | K11: =VLOOKUP($C11,Customer_Dim_Cleaned!$A$2:$H$501,2,FALSE) -> David Pierce | L11: =VLOOKUP($D11,Product_Dim_Cleaned!$A$2:$F$101,2,FALSE) -> Modern Wall Clock | M11: =VLOOKUP($E11,Store_Dim_Cleaned!$A$2:$E$21,2,FALSE) -> Rivera-Warner
A12: SALE10 | B12: 45335 | C12: CUST1065 | D12: PROD24 | E12: STORE14 | F12: 1 | G12: 278.63 | H12: 0.07 | I12: Credit Card | J12: 259.1259 | K12: =VLOOKUP($C12,Customer_Dim_Cleaned!$A$2:$H$501,2,FALSE) -> Michael Thomas | L12: =VLOOKUP($D12,Product_Dim_Cleaned!$A$2:$F$101,2,FALSE) -> Foldable Camping Chair | M12: =VLOOKUP($E12,Store_Dim_Cleaned!$A$2:$E$21,2,FALSE) -> Mcdonald Inc
A13: SALE11 | B13: 45801 | C13: CUST1320 | D13: PROD39 | E13: STORE1 | F13: 4 | G13: 286.92 | H13: 0.17 | I13: Credit Card | J13: 952.5744 | K13: =VLOOKUP($C13,Customer_Dim_Cleaned!$A$2:$H$501,2,FALSE) -> Jessica Gonzalez | L13: =VLOOKUP($D13,Product_Dim_Cleaned!$A$2:$F$101,2,FALSE) -> Portable Power Bank | M13: =VLOOKUP($E13,Store_Dim_Cleaned!$A$2:$E$21,2,FALSE) -> Martinez, Adkins and Johnson
... A2001: SALE1999 | B2001: 45267 | C2001: CUST1023 | D2001: PROD76 | E2001: STORE19 | F2001: 3 | G2001: 68.45 | H2001: 0.17 | I2001: PayPal | J2001: 170.4405 | K2001: =VLOOKUP($C2001,Customer_Dim_Cleaned!$A$2:$H$501,2,FALSE) -> Jonathan Steele | L2001: =VLOOKUP($D2001,Product_Dim_Cleaned!$A$2:$F$101,2,FALSE) -> Wireless Mouse | M2001: =VLOOKUP($E2001,Store_Dim_Cleaned!$A$2:$E$21,2,FALSE) -> Mann-Austin

Sheet Pivot Table
A1: Month | B1: Sum of Total_Amount | C1: Sum of Quantity | E1: Store Type | F1: Sum of Total_Amount | H1: Loyalty Level | I1: Sum of Total_Amount
A2: Jan | B2: 174449.14 | C2: 398 | E2: Flagship | F2: 848576.67 | H2: Bronze | I2: 522623.38
A3: Feb | B3: 155073.94 | C3: 370 | E3: Online | F3: 914253.52 | H3: Gold | I3: 517622.06
A4: Mar | B4: 210704.52 | C4: 467 | E4: Outlet | F4: 411564.51 | H4: Platinum | I4: 673616.5
A5: Apr | B5: 192864.04 | C5: 426 | E5: Grand Total | F5: 2174394.7 | H5: Silver | I5: 460532.76
A6: May | B6: 146511.96 | C6: 381 | H6: Grand Total | I6: 2174394.7
A7: Jun | B7: 162640.02 | C7: 382 | E7: Region | F7: Sum of Total_Amount
A8: Jul | B8: 194711.82 | C8: 458 | E8: East | F8: 622404.32 | H8: Month | I8: Sum of Total_Amount
A9: Aug | B9: 192159.73 | C9: 426 | E9: North | F9: 646100.88 | H9: Jan | I9: 174449.14
A10: Sep | B10: 188570.18 | C10: 420 | E10: South | F10: 635213.1 | H10: Feb | I10: 155073.94
A11: Oct | B11: 186168.21 | C11: 419 | E11: West | F11: 270676.41 | H11: Mar | I11: 210704.52
A12: Nov | B12: 187386.17 | C12: 413 | E12: Grand Total | F12: 2174394.7 | H12: Apr | I12: 192864.04
A13: Dec | B13: 183154.98 | C13: 404 | H13: May | I13: 146511.96
A14: Grand Total | B14: 2174394.7 | C14: 4964 | E14: Product Name | F14: Sum of Total_Amount | H14: Jun | I14: 162640.02
E15: Gaming Mechanical Keyboard | F15: 34699.833 | H15: Jul | I15: 194711.82
A16: Category | B16: Sum of Total_Amount | E16: Men's Casual Sneakers | F16: 35489.62 | H16: Aug | I16: 192159.73
A17: Beauty | B17: 321561.33 | E17: Portable Power Bank | F17: 41852.503 | H17: Sep | I17: 188570.18
A18: Clothing | B18: 379216.04 | E18: Shin Guards – Adult | F18: 38281.015 | H18: Oct | I18: 186168.21
A19: Electronics | B19: 504311.35 | E19: Women's High Heels | F19: 33993.659 | H19: Nov | I19: 187386.17
A20: Home | B20: 427295.8 | E20: Grand Total | F20: 184316.63 | H20: Dec | I20: 183154.98
A21: Sports | B21: 542010.17 | H21: Grand Total | I21: 2174394.7
A22: Grand Total | B22: 2174394.7

Sheet Charts

Sheet Dashboard
A1: E-Commerce Sales Performance Dashboard
